[{"Class of": "2019", "Admission Decision": "Accepted", "GPA": "3.34", "SAT Single": 1130, "ACT": "", "Major": "Political Science", "AP/IB/Coll": "3", "Honors": "2", "App Deadline": "", "Home State": "CA", "Applied Test Optional": null}, {"Class of": "2015", "Admission Decision": "Not Accepted", "GPA": "2.54", "SAT Single": 900, "ACT": "", "Major": "Business", "AP/IB/Coll": "4", "Honors": "1", "App Deadline": "", "Home State": "NJ", "Applied Test Optional": null}, {"Class of": "2016", "Admission Decision": "Accepted", "GPA": "2.4", "SAT Single": 1150, "ACT": "", "Major": "", "AP/IB/Coll": "4", "Honors": "", "App Deadline": "", "Home State": "NY", "Applied Test Optional": null}, {"Class of": "2016", "Admission Decision": "Accepted", "GPA": "3.3", "SAT Single": 990, "ACT": "", "Major": "", "AP/IB/Coll": "", "Honors": "", "App Deadline": "", "Home State": "CA", "Applied Test Optional": null}, {"Class of": "2019", "Admission Decision": "Accepted", "GPA": "3.2", "SAT Single": 1190, "ACT": "", "Major": "Engineering - Electrical", "AP/IB/Coll": "3", "Honors": "9", "App Deadline": "", "Home State": "NY", "Applied Test Optional": null}, {"Class of": "2020", "Admission Decision": "Accepted", "GPA": "3.94", "SAT Single": "", "ACT": "28", "Major": "Undecided", "AP/IB/Coll": "2", "Honors": "", "App Deadline": "", "Home State": "NY", "Applied Test Optional": null}, {"Class of": "2020", "Admission Decision": "Accepted", "GPA": "2.33", "SAT Single": 1360, "ACT": "", "Major": "Biology", "AP/IB/Coll": "14", "Honors": "", "App Deadline": "", "Home State": "NY", "Applied Test Optional": null}, {"Class of": "2020", "Admission Decision": "Accepted", "GPA": "3.64", "SAT Single": "", "ACT": "30", "Major": "Communication", "AP/IB/Coll": "28", "Honors": "2", "App Deadline": "", "Home State": "NY", "Applied Test Optional": null}, {"Class of": "2021", "Admission Decision": "Accepted", "GPA": "3.3", "Applied Test Optional": true, "SAT Single": 1150, "ACT": "", "Major": "English", "AP/IB/Coll": "0", "Honors": "4", "App Deadline": "EA", "Home State": "NY"}, {"Class of": "2021", "Admission Decision": "Accepted", "GPA": "4", "Applied Test Optional": false, "SAT Single": "", "ACT": "34", "Major": "Biological Sciences", "AP/IB/Coll": "12", "Honors": "10", "App Deadline": "", "Home State": "NY"}, {"Class of": "2021", "Admission Decision": "Accepted", "GPA": "3.8", "Applied Test Optional": false, "SAT Single": "", "ACT": "", "Major": "Philosophy - Political Science", "AP/IB/Coll": "8", "Honors": "1", "App Deadline": "", "Home State": "NY"}, {"Class of": "2021", "Admission Decision": "Accepted", "GPA": "", "Applied Test Optional": false, "SAT Single": "", "ACT": "", "Major": "Psychology", "AP/IB/Coll": "6", "Honors": "14", "App Deadline": "Rolling", "Home State": "NY"}, {"Class of": "2021", "Admission Decision": "Accepted", "GPA": "", "Applied Test Optional": false, "SAT Single": "", "ACT": "", "Major": "Biomedical Sciences", "AP/IB/Coll": "10", "Honors": "2", "App Deadline": "Early Action", "Home State": "NY"}, {"Class of": "2021", "Admission Decision": "Accepted", "GPA": "", "Applied Test Optional": false, "SAT Single": "", "ACT": "", "Major": "Psychology", "AP/IB/Coll": "6", "Honors": "14", "App Deadline": "Early Action", "Home State": "NY"}, {"Class of": "2021", "Admission Decision": "Accepted", "GPA": "", "Applied Test Optional": false, "SAT Single": "", "ACT": "", "Major": "History", "AP/IB/Coll": "10", "Honors": "30", "App Deadline": "Early Action", "Home State": "NY"}, {"Class of": "2021", "Admission Decision": "Accepted", "GPA": "", "Applied Test Optional": false, "SAT Single": "", "ACT": "", "Major": "History", "AP/IB/Coll": "10", "Honors": "30", "App Deadline": "Early Action", "Home State": "NY"}, {"Class of": "2021", "Admission Decision": "Accepted", "GPA": "", "Applied Test Optional": false, "SAT Single": "", "ACT": "", "Major": "Computer Science", "AP/IB/Coll": "16", "Honors": "16", "App Deadline": "Early Action", "Home State": "NY"}, {"Class of": "2021", "Admission Decision": "Accepted", "GPA": "", "Applied Test Optional": false, "SAT Single": "", "ACT": "", "Major": "Political Science", "AP/IB/Coll": "4", "Honors": "42", "App Deadline": "Early Action", "Home State": "NY"}, {"Class of": "2021", "Admission Decision": "Accepted", "GPA": "", "Applied Test Optional": false, "SAT Single": "", "ACT": "", "Major": "Chemical Engineering", "AP/IB/Coll": "10", "Honors": "0", "App Deadline": "Early Action", "Home State": "NY"}]