[{"Class of": "2016", "Admission Decision": "Accepted", "GPA": "4", "SAT Single": 1540, "ACT": "", "Major": "Biochemistry", "AP/IB/Coll": "27", "Honors": "10", "App Deadline": "", "Home State": "OH", "Applied Test Optional": null}, {"Class of": "2018", "Admission Decision": "Not Accepted", "GPA": "3.75", "SAT Single": "", "ACT": "32", "Major": "Biology - Accelerated Med", "AP/IB/Coll": "18", "Honors": "20", "App Deadline": "", "Home State": "NJ", "Applied Test Optional": null}, {"Class of": "2018", "Admission Decision": "Accepted", "GPA": "3.75", "SAT Single": "", "ACT": "32", "Major": "Biology", "AP/IB/Coll": "18", "Honors": "20", "App Deadline": "", "Home State": "NJ", "Applied Test Optional": null}, {"Class of": "2017", "Admission Decision": "Accepted", "GPA": "3.54", "SAT Single": 1080, "ACT": "", "Major": "Nursing", "AP/IB/Coll": "14", "Honors": "", "App Deadline": "", "Home State": "CA", "Applied Test Optional": null}, {"Class of": "2016", "Admission Decision": "Accepted", "GPA": "4", "SAT Single": 1540, "ACT": "", "Major": "Biology - Accelerated Med", "AP/IB/Coll": "27", "Honors": "10", "App Deadline": "", "Home State": "OH", "Applied Test Optional": null}]
