[{"Class of": "2017", "Admission Decision": "Accepted", "GPA": "3.12", "SAT Single": "", "ACT": "", "Major": "Undecided", "AP/IB/Coll": "0", "Honors": "4", "App Deadline": "EA", "Home State": "NJ", "Applied Test Optional": null}, {"Class of": "2018", "Admission Decision": "Accepted", "GPA": "3.72", "SAT Single": "", "ACT": "29", "Major": "Undecided - Liberal Arts & Sciences", "AP/IB/Coll": "10", "Honors": "6", "App Deadline": "EA", "Home State": "CA", "Applied Test Optional": null}, {"Class of": "2019", "Admission Decision": "Accepted", "GPA": "3.95", "SAT Single": "", "ACT": "33", "Major": "Business", "AP/IB/Coll": "12", "Honors": "6", "App Deadline": "EA", "Home State": "CA", "Applied Test Optional": null}, {"Class of": "2018", "Admission Decision": "Accepted", "GPA": "3.5", "SAT Single": 1190, "ACT": "24", "Major": "Undecided", "AP/IB/Coll": "8", "Honors": "6", "App Deadline": "", "Home State": "CA", "Applied Test Optional": null}, {"Class of": "2018", "Admission Decision": "Accepted", "GPA": "3.26", "SAT Single": 1200, "ACT": "", "Major": "Psychology", "AP/IB/Coll": "2", "Honors": "2", "App Deadline": "", "Home State": "CA", "Applied Test Optional": null}, {"Class of": "2019", "Admission Decision": "Accepted", "GPA": "3.7", "SAT Single": 1350, "ACT": "", "Major": "Education", "AP/IB/Coll": "2", "Honors": "0", "App Deadline": "EA", "Home State": "IL", "Applied Test Optional": null}, {"Class of": "2018", "Admission Decision": "Accepted", "GPA": "2.95", "SAT Single": "", "ACT": "28", "Major": "Engineering - Computer", "AP/IB/Coll": "7", "Honors": "4", "App Deadline": "", "Home State": "CA", "Applied Test Optional": null}, {"Class of": "2017", "Admission Decision": "Accepted", "GPA": "3.5", "SAT Single": 1330, "ACT": "", "Major": "Business", "AP/IB/Coll": "10", "Honors": "7", "App Deadline": "", "Home State": "CA", "Applied Test Optional": null}, {"Class of": "2019", "Admission Decision": "Accepted", "GPA": "3.5", "SAT Single": 1230, "ACT": "", "Major": "Environmental Science - Earth and Oceanographic Science", "AP/IB/Coll": "8", "Honors": "12", "App Deadline": "", "Home State": "CA", "Applied Test Optional": null}, {"Class of": "2018", "Admission Decision": "Accepted", "GPA": "3.55", "SAT Single": "", "ACT": "25", "Major": "Business", "AP/IB/Coll": "8", "Honors": "2", "App Deadline": "", "Home State": "CA", "Applied Test Optional": null}, {"Class of": "2015", "Admission Decision": "Accepted", "GPA": "3.04", "SAT Single": 1150, "ACT": "", "Major": "Undecided", "AP/IB/Coll": "0", "Honors": "0", "App Deadline": "", "Home State": "CA", "Applied Test Optional": null}, {"Class of": "2018", "Admission Decision": "Accepted", "GPA": "3.2", "SAT Single": 1410, "ACT": "", "Major": "Engineering - Chemical", "AP/IB/Coll": "10", "Honors": "12", "App Deadline": "", "Home State": "TX", "Applied Test Optional": null}, {"Class of": "2019", "Admission Decision": "Accepted", "GPA": "3.17", "SAT Single": "", "ACT": "24", "Major": "Education", "AP/IB/Coll": "4", "Honors": "0", "App Deadline": "", "Home State": "CA", "Applied Test Optional": null}, {"Class of": "2017", "Admission Decision": "Accepted", "GPA": "3.8", "SAT Single": "", "ACT": "", "Major": "English", "AP/IB/Coll": "", "Honors": "", "App Deadline": "", "Home State": "MI", "Applied Test Optional": null}, {"Class of": "2017", "Admission Decision": "Accepted", "GPA": "2.85", "SAT Single": "", "ACT": "", "Major": "Business - Finance", "AP/IB/Coll": "6", "Honors": "8", "App Deadline": "", "Home State": "CA", "Applied Test Optional": null}, {"Class of": "2017", "Admission Decision": "Accepted", "GPA": "3.13", "SAT Single": "", "ACT": "", "Major": "Business - Marketing", "AP/IB/Coll": "2", "Honors": "0", "App Deadline": "", "Home State": "CA", "Applied Test Optional": null}, {"Class of": "2017", "Admission Decision": "Deferred", "GPA": "2.85", "SAT Single": "", "ACT": "", "Major": "Undecided", "AP/IB/Coll": "0", "Honors": "0", "App Deadline": "", "Home State": "CA", "Applied Test Optional": null}, {"Class of": "2018", "Admission Decision": "Accepted", "GPA": "3.79", "SAT Single": "", "ACT": "29", "Major": "Business", "AP/IB/Coll": "8", "Honors": "8", "App Deadline": "", "Home State": "CT", "Applied Test Optional": null}, {"Class of": "2019", "Admission Decision": "Accepted", "GPA": "3.3", "SAT Single": "", "ACT": "32", "Major": "Undecided", "AP/IB/Coll": "4", "Honors": "7", "App Deadline": "EA", "Home State": "CT", "Applied Test Optional": null}, {"Class of": "2019", "Admission Decision": "Accepted", "GPA": "3.63", "SAT Single": "", "ACT": "28", "Major": "Communication", "AP/IB/Coll": "6", "Honors": "0", "App Deadline": "EA", "Home State": "CA", "Applied Test Optional": null}, {"Class of": "2018", "Admission Decision": "Accepted", "GPA": "3.18", "SAT Single": "", "ACT": "30", "Major": "Undecided", "AP/IB/Coll": "14", "Honors": "2", "App Deadline": "", "Home State": "CA", "Applied Test Optional": null}, {"Class of": "2019", "Admission Decision": "Accepted", "GPA": "2.97", "SAT Single": 1240, "ACT": "", "Major": "Sociology", "AP/IB/Coll": "", "Honors": "", "App Deadline": "EA", "Home State": "CA", "Applied Test Optional": null}, {"Class of": "2019", "Admission Decision": "Accepted", "GPA": "3.72", "SAT Single": "", "ACT": "31", "Major": "Journalism", "AP/IB/Coll": "6", "Honors": "0", "App Deadline": "EA", "Home State": "CA", "Applied Test Optional": null}, {"Class of": "2019", "Admission Decision": "Accepted", "GPA": "3", "SAT Single": 1330, "ACT": "28", "Major": "Undecided", "AP/IB/Coll": "14", "Honors": "18", "App Deadline": "EA", "Home State": "CA", "Applied Test Optional": null}, {"Class of": "2019", "Admission Decision": "Accepted", "GPA": "4", "SAT Single": 1580, "ACT": "", "Major": "Computer Science", "AP/IB/Coll": "15", "Honors": "4", "App Deadline": "", "Home State": "NY", "Applied Test Optional": null}, {"Class of": "2017", "Admission Decision": "Accepted", "GPA": "2.8", "SAT Single": "", "ACT": "", "Major": "Pre - Vet", "AP/IB/Coll": "6", "Honors": "", "App Deadline": "", "Home State": "CA", "Applied Test Optional": null}, {"Class of": "2019", "Admission Decision": "Not Accepted", "GPA": "2.65", "SAT Single": "", "ACT": "21", "Major": "Business", "AP/IB/Coll": "2", "Honors": "2", "App Deadline": "", "Home State": "CA", "Applied Test Optional": null}, {"Class of": "2017", "Admission Decision": "Accepted", "GPA": "3.08", "SAT Single": "", "ACT": "", "Major": "Communication", "AP/IB/Coll": "2", "Honors": "2", "App Deadline": "", "Home State": "CA", "Applied Test Optional": null}, {"Class of": "2018", "Admission Decision": "Accepted", "GPA": "3.47", "SAT Single": "", "ACT": "26", "Major": "Psychology", "AP/IB/Coll": "4", "Honors": "0", "App Deadline": "", "Home State": "CA", "Applied Test Optional": null}, {"Class of": "2017", "Admission Decision": "Accepted", "GPA": "4", "SAT Single": "", "ACT": "", "Major": "Engineering - Mechanical", "AP/IB/Coll": "16", "Honors": "18", "App Deadline": "", "Home State": "TX", "Applied Test Optional": null}, {"Class of": "2019", "Admission Decision": "Accepted", "GPA": "3.78", "SAT Single": "", "ACT": "30", "Major": "Business - Management", "AP/IB/Coll": "8", "Honors": "14", "App Deadline": "", "Home State": "NJ", "Applied Test Optional": null}, {"Class of": "2017", "Admission Decision": "Accepted", "GPA": "3.67", "SAT Single": "", "ACT": "", "Major": "Biology - Biochemistry & Molecular", "AP/IB/Coll": "16", "Honors": "20", "App Deadline": "", "Home State": "TX", "Applied Test Optional": null}, {"Class of": "2019", "Admission Decision": "Accepted", "GPA": "3.65", "SAT Single": "", "ACT": "29", "Major": "Art - Studio", "AP/IB/Coll": "8", "Honors": "18", "App Deadline": "", "Home State": "MI", "Applied Test Optional": null}, {"Class of": "2017", "Admission Decision": "Accepted", "GPA": "3.08", "SAT Single": 1260, "ACT": "", "Major": "Undecided", "AP/IB/Coll": "6", "Honors": "10", "App Deadline": "", "Home State": "MA", "Applied Test Optional": null}, {"Class of": "2018", "Admission Decision": "Accepted", "GPA": "3.25", "SAT Single": 1500, "ACT": "", "Major": "Computer Science", "AP/IB/Coll": "20", "Honors": "14", "App Deadline": "", "Home State": "TX", "Applied Test Optional": null}, {"Class of": "2018", "Admission Decision": "Accepted", "GPA": "", "SAT Single": 1260, "ACT": "29", "Major": "Linguistics", "AP/IB/Coll": "", "Honors": "", "App Deadline": "EA", "Home State": "MI", "Applied Test Optional": null}, {"Class of": "2015", "Admission Decision": "Accepted", "GPA": "3.54", "SAT Single": "", "ACT": "", "Major": "Undecided", "AP/IB/Coll": "8", "Honors": "5", "App Deadline": "", "Home State": "CA", "Applied Test Optional": null}, {"Class of": "2017", "Admission Decision": "Accepted", "GPA": "3.45", "SAT Single": "", "ACT": "", "Major": "Engineering - Biomedical", "AP/IB/Coll": "10", "Honors": "10", "App Deadline": "", "Home State": "CA", "Applied Test Optional": null}, {"Class of": "2015", "Admission Decision": "Accepted", "GPA": "3.67", "SAT Single": "", "ACT": "", "Major": "Undecided", "AP/IB/Coll": "", "Honors": "4", "App Deadline": "", "Home State": "CA", "Applied Test Optional": null}, {"Class of": "2016", "Admission Decision": "Accepted", "GPA": "3", "SAT Single": 1080, "ACT": "", "Major": "Nursing", "AP/IB/Coll": "14", "Honors": "", "App Deadline": "", "Home State": "TX", "Applied Test Optional": null}, {"Class of": "2017", "Admission Decision": "Accepted", "GPA": "2.8", "SAT Single": "", "ACT": "", "Major": "Criminal Justice", "AP/IB/Coll": "10", "Honors": "0", "App Deadline": "", "Home State": "TX", "Applied Test Optional": null}, {"Class of": "2019", "Admission Decision": "Accepted", "GPA": "3.44", "SAT Single": "", "ACT": "32", "Major": "Art - Game Design", "AP/IB/Coll": "4", "Honors": "6", "App Deadline": "", "Home State": "CO", "Applied Test Optional": null}, {"Class of": "2015", "Admission Decision": "Accepted", "GPA": "3.36", "SAT Single": "", "ACT": "", "Major": "Undecided", "AP/IB/Coll": "12", "Honors": "6", "App Deadline": "", "Home State": "CA", "Applied Test Optional": null}, {"Class of": "2016", "Admission Decision": "Accepted", "GPA": "3.06", "SAT Single": "", "ACT": "", "Major": "Nursing", "AP/IB/Coll": "", "Honors": "", "App Deadline": "", "Home State": "CA", "Applied Test Optional": null}, {"Class of": "2018", "Admission Decision": "Accepted", "GPA": "3.39", "SAT Single": "", "ACT": "30", "Major": "Undecided - Business", "AP/IB/Coll": "8", "Honors": "5", "App Deadline": "", "Home State": "CA", "Applied Test Optional": null}, {"Class of": "2018", "Admission Decision": "Accepted", "GPA": "2.72", "SAT Single": "", "ACT": "25", "Major": "Business - Marketing", "AP/IB/Coll": "0", "Honors": "6", "App Deadline": "", "Home State": "CA", "Applied Test Optional": null}, {"Class of": "2018", "Admission Decision": "Accepted", "GPA": "3.13", "SAT Single": "", "ACT": "24", "Major": "Business", "AP/IB/Coll": "2", "Honors": "4", "App Deadline": "", "Home State": "CA", "Applied Test Optional": null}, {"Class of": "2018", "Admission Decision": "Accepted", "GPA": "3.71", "SAT Single": "", "ACT": "33", "Major": "English", "AP/IB/Coll": "11", "Honors": "4", "App Deadline": "", "Home State": "CA", "Applied Test Optional": null}, {"Class of": "2018", "Admission Decision": "Accepted", "GPA": "3.52", "SAT Single": "", "ACT": "24", "Major": "Business", "AP/IB/Coll": "1", "Honors": "", "App Deadline": "", "Home State": "CA", "Applied Test Optional": null}, {"Class of": "2019", "Admission Decision": "Accepted", "GPA": "3.5", "SAT Single": "", "ACT": "24", "Major": "Social Work", "AP/IB/Coll": "0", "Honors": "34", "App Deadline": "EA", "Home State": "FL", "Applied Test Optional": null}, {"Class of": "2017", "Admission Decision": "Accepted", "GPA": "3.22", "SAT Single": "", "ACT": "", "Major": "Economics", "AP/IB/Coll": "6", "Honors": "9", "App Deadline": "EA", "Home State": "NJ", "Applied Test Optional": null}, {"Class of": "2017", "Admission Decision": "Accepted", "GPA": "4", "SAT Single": "", "ACT": "", "Major": "Biology", "AP/IB/Coll": "6", "Honors": "6", "App Deadline": "", "Home State": "CA", "Applied Test Optional": null}, {"Class of": "2016", "Admission Decision": "Accepted", "GPA": "3.12", "SAT Single": 1060, "ACT": "", "Major": "Business - Finance", "AP/IB/Coll": "", "Honors": "5", "App Deadline": "", "Home State": "CA", "Applied Test Optional": null}, {"Class of": "2015", "Admission Decision": "Accepted", "GPA": "2.74", "SAT Single": "", "ACT": "", "Major": "Undecided", "AP/IB/Coll": "0", "Honors": "0", "App Deadline": "", "Home State": "CA", "Applied Test Optional": null}, {"Class of": "2017", "Admission Decision": "Accepted", "GPA": "3.88", "SAT Single": "", "ACT": "", "Major": "Undecided", "AP/IB/Coll": "0", "Honors": "0", "App Deadline": "", "Home State": "CA", "Applied Test Optional": null}, {"Class of": "2019", "Admission Decision": "Accepted", "GPA": "4", "SAT Single": "", "ACT": "31", "Major": "Business", "AP/IB/Coll": "20", "Honors": "10", "App Deadline": "EA", "Home State": "WA", "Applied Test Optional": null}, {"Class of": "2017", "Admission Decision": "Accepted", "GPA": "3.73", "SAT Single": "", "ACT": "", "Major": "Health Science - Nutrition", "AP/IB/Coll": "10", "Honors": "10", "App Deadline": "", "Home State": "CA", "Applied Test Optional": null}, {"Class of": "2017", "Admission Decision": "Accepted", "GPA": "3.36", "SAT Single": "", "ACT": "", "Major": "Psychology", "AP/IB/Coll": "6", "Honors": "0", "App Deadline": "", "Home State": "CA", "Applied Test Optional": null}, {"Class of": "2019", "Admission Decision": "Accepted", "GPA": "3.88", "SAT Single": 1590, "ACT": "", "Major": "Engineering - Materials", "AP/IB/Coll": "21", "Honors": "12", "App Deadline": "", "Home State": "MI", "Applied Test Optional": null}, {"Class of": "2016", "Admission Decision": "Accepted", "GPA": "3.67", "SAT Single": 1180, "ACT": "", "Major": "Business - Marketing", "AP/IB/Coll": "2", "Honors": "4", "App Deadline": "", "Home State": "NJ", "Applied Test Optional": null}, {"Class of": "2016", "Admission Decision": "Accepted", "GPA": "2.9", "SAT Single": 1180, "ACT": "", "Major": "Business - Economics", "AP/IB/Coll": "2", "Honors": "", "App Deadline": "", "Home State": "CA", "Applied Test Optional": null}, {"Class of": "2018", "Admission Decision": "Accepted", "GPA": "3.14", "SAT Single": 1120, "ACT": "30", "Major": "Business - Management", "AP/IB/Coll": "12", "Honors": "6", "App Deadline": "", "Home State": "CA", "Applied Test Optional": null}, {"Class of": "2018", "Admission Decision": "Accepted", "GPA": "3.86", "SAT Single": "", "ACT": "29", "Major": "Biology - Animal & Vet Science", "AP/IB/Coll": "18", "Honors": "18", "App Deadline": "", "Home State": "CA", "Applied Test Optional": null}, {"Class of": "2019", "Admission Decision": "Accepted", "GPA": "3.13", "SAT Single": 1360, "ACT": "", "Major": "Undecided - Liberal Arts & Sciences", "AP/IB/Coll": "14", "Honors": "22", "App Deadline": "EA", "Home State": "MD", "Applied Test Optional": null}, {"Class of": "2018", "Admission Decision": "Accepted", "GPA": "3.84", "SAT Single": "", "ACT": "33", "Major": "Engineering", "AP/IB/Coll": "4", "Honors": "6", "App Deadline": "", "Home State": "CA", "Applied Test Optional": null}, {"Class of": "2019", "Admission Decision": "Accepted", "GPA": "3.23", "SAT Single": "", "ACT": "25", "Major": "Business - Sports Management", "AP/IB/Coll": "0", "Honors": "6", "App Deadline": "EA", "Home State": "NJ", "Applied Test Optional": null}, {"Class of": "2017", "Admission Decision": "Accepted", "GPA": "3.25", "SAT Single": 1240, "ACT": "", "Major": "Undecided", "AP/IB/Coll": "", "Honors": "", "App Deadline": "", "Home State": "CT", "Applied Test Optional": null}, {"Class of": "2018", "Admission Decision": "Accepted", "GPA": "3.17", "SAT Single": "", "ACT": "31", "Major": "Undecided - Business", "AP/IB/Coll": "8", "Honors": "2", "App Deadline": "", "Home State": "CA", "Applied Test Optional": null}, {"Class of": "2017", "Admission Decision": "Accepted", "GPA": "3.63", "SAT Single": "", "ACT": "", "Major": "Business", "AP/IB/Coll": "0", "Honors": "0", "App Deadline": "", "Home State": "CA", "Applied Test Optional": null}, {"Class of": "2016", "Admission Decision": "Accepted", "GPA": "2.76", "SAT Single": "", "ACT": "", "Major": "", "AP/IB/Coll": "6", "Honors": "4", "App Deadline": "", "Home State": "WA", "Applied Test Optional": null}, {"Class of": "2016", "Admission Decision": "Accepted", "GPA": "2.85", "SAT Single": 1140, "ACT": "", "Major": "Business", "AP/IB/Coll": "12", "Honors": "8", "App Deadline": "", "Home State": "CA", "Applied Test Optional": null}, {"Class of": "2015", "Admission Decision": "Accepted", "GPA": "2.65", "SAT Single": 1300, "ACT": "", "Major": "Neuroscience", "AP/IB/Coll": "14", "Honors": "6", "App Deadline": "", "Home State": "CA", "Applied Test Optional": null}, {"Class of": "2019", "Admission Decision": "Accepted", "GPA": "3.46", "SAT Single": 1390, "ACT": "", "Major": "Chemistry", "AP/IB/Coll": "6", "Honors": "6", "App Deadline": "EA", "Home State": "CA", "Applied Test Optional": null}, {"Class of": "2017", "Admission Decision": "Accepted", "GPA": "2.95", "SAT Single": "", "ACT": "", "Major": "Biology - Zoology", "AP/IB/Coll": "4", "Honors": "2", "App Deadline": "", "Home State": "CA", "Applied Test Optional": null}, {"Class of": "2017", "Admission Decision": "Accepted", "GPA": "3.22", "SAT Single": "", "ACT": "", "Major": "Undecided", "AP/IB/Coll": "3", "Honors": "0", "App Deadline": "", "Home State": "CA", "Applied Test Optional": null}, {"Class of": "2016", "Admission Decision": "Accepted", "GPA": "2.65", "SAT Single": 1030, "ACT": "", "Major": "Communication", "AP/IB/Coll": "", "Honors": "2", "App Deadline": "", "Home State": "CA", "Applied Test Optional": null}, {"Class of": "2017", "Admission Decision": "Accepted", "GPA": "3.42", "SAT Single": "", "ACT": "", "Major": "Economics", "AP/IB/Coll": "19", "Honors": "6", "App Deadline": "", "Home State": "CA", "Applied Test Optional": null}, {"Class of": "2019", "Admission Decision": "Accepted", "GPA": "3.95", "SAT Single": 1590, "ACT": "", "Major": "Pre - Health Sciences", "AP/IB/Coll": "24", "Honors": "6", "App Deadline": "EA", "Home State": "MI", "Applied Test Optional": null}, {"Class of": "2019", "Admission Decision": "Accepted", "GPA": "3.3", "SAT Single": "", "ACT": "", "Major": "Engineering", "AP/IB/Coll": "14", "Honors": "10", "App Deadline": "EA", "Home State": "CO", "Applied Test Optional": null}, {"Class of": "2017", "Admission Decision": "Accepted", "GPA": "3.25", "SAT Single": "", "ACT": "", "Major": "Journalism", "AP/IB/Coll": "6", "Honors": "0", "App Deadline": "", "Home State": "CA", "Applied Test Optional": null}, {"Class of": "2017", "Admission Decision": "Accepted", "GPA": "3.31", "SAT Single": 1120, "ACT": "", "Major": "Biology", "AP/IB/Coll": "6", "Honors": "12", "App Deadline": "", "Home State": "CA", "Applied Test Optional": null}, {"Class of": "2019", "Admission Decision": "Accepted", "GPA": "2.7", "SAT Single": 1380, "ACT": "", "Major": "General Studies", "AP/IB/Coll": "8", "Honors": "21", "App Deadline": "", "Home State": "CT", "Applied Test Optional": null}, {"Class of": "2019", "Admission Decision": "Accepted", "GPA": "2.6", "SAT Single": "", "ACT": "30", "Major": "Undecided", "AP/IB/Coll": "1", "Honors": "0", "App Deadline": "EA", "Home State": "CT", "Applied Test Optional": null}, {"Class of": "2015", "Admission Decision": "Accepted", "GPA": "3.25", "SAT Single": "", "ACT": "", "Major": "Undecided", "AP/IB/Coll": "10", "Honors": "0", "App Deadline": "", "Home State": "CA", "Applied Test Optional": null}, {"Class of": "2019", "Admission Decision": "Accepted", "GPA": "3.67", "SAT Single": "", "ACT": "31", "Major": "Communication", "AP/IB/Coll": "10", "Honors": "10", "App Deadline": "EA", "Home State": "MD", "Applied Test Optional": null}, {"Class of": "2019", "Admission Decision": "Accepted", "GPA": "3", "SAT Single": 1230, "ACT": "30", "Major": "Pre - Nursing", "AP/IB/Coll": "", "Honors": "6", "App Deadline": "EA", "Home State": "CA", "Applied Test Optional": null}, {"Class of": "2015", "Admission Decision": "Accepted", "GPA": "3.62", "SAT Single": 1070, "ACT": "", "Major": "Undecided", "AP/IB/Coll": "4", "Honors": "2", "App Deadline": "", "Home State": "CA", "Applied Test Optional": null}, {"Class of": "2017", "Admission Decision": "Accepted", "GPA": "3.7", "SAT Single": "", "ACT": "", "Major": "Political Science", "AP/IB/Coll": "", "Honors": "", "App Deadline": "", "Home State": "MI", "Applied Test Optional": null}, {"Class of": "2019", "Admission Decision": "Accepted", "GPA": "3.81", "SAT Single": "", "ACT": "32", "Major": "Biology", "AP/IB/Coll": "10", "Honors": "2", "App Deadline": "EA", "Home State": "CA", "Applied Test Optional": null}, {"Class of": "2019", "Admission Decision": "Accepted", "GPA": "3.3", "SAT Single": "", "ACT": "24", "Major": "Business", "AP/IB/Coll": "8", "Honors": "10", "App Deadline": "", "Home State": "CA", "Applied Test Optional": null}, {"Class of": "2018", "Admission Decision": "Accepted", "GPA": "3.48", "SAT Single": "", "ACT": "25", "Major": "Business", "AP/IB/Coll": "6", "Honors": "0", "App Deadline": "EA", "Home State": "CA", "Applied Test Optional": null}, {"Class of": "2018", "Admission Decision": "Accepted", "GPA": "3.09", "SAT Single": 1110, "ACT": "", "Major": "Psychology", "AP/IB/Coll": "", "Honors": "", "App Deadline": "", "Home State": "CA", "Applied Test Optional": null}, {"Class of": "2019", "Admission Decision": "Accepted", "GPA": "3.84", "SAT Single": 1350, "ACT": "29", "Major": "Engineering - Mechanical", "AP/IB/Coll": "12", "Honors": "14", "App Deadline": "EA", "Home State": "CA", "Applied Test Optional": null}, {"Class of": "2019", "Admission Decision": "Accepted", "GPA": "3.6", "SAT Single": "", "ACT": "27", "Major": "Journalism", "AP/IB/Coll": "12", "Honors": "8", "App Deadline": "EA", "Home State": "CA", "Applied Test Optional": null}, {"Class of": "2019", "Admission Decision": "Accepted", "GPA": "3.02", "SAT Single": 1140, "ACT": "", "Major": "Education - Elementary", "AP/IB/Coll": "2", "Honors": "0", "App Deadline": "EA", "Home State": "NY", "Applied Test Optional": null}, {"Class of": "2017", "Admission Decision": "Accepted", "GPA": "3.21", "SAT Single": "", "ACT": "", "Major": "International Studies", "AP/IB/Coll": "18", "Honors": "4", "App Deadline": "", "Home State": "TX", "Applied Test Optional": null}, {"Class of": "2019", "Admission Decision": "Accepted", "GPA": "3.76", "SAT Single": 1560, "ACT": "", "Major": "Computer Science", "AP/IB/Coll": "24", "Honors": "10", "App Deadline": "", "Home State": "CA", "Applied Test Optional": null}, {"Class of": "2015", "Admission Decision": "Not Accepted", "GPA": "2.5", "SAT Single": "", "ACT": "", "Major": "Physics", "AP/IB/Coll": "10", "Honors": "22", "App Deadline": "", "Home State": "NC", "Applied Test Optional": null}, {"Class of": "2017", "Admission Decision": "Accepted", "GPA": "3.4", "SAT Single": "", "ACT": "", "Major": "Engineering - Civil", "AP/IB/Coll": "14", "Honors": "10", "App Deadline": "", "Home State": "CA", "Applied Test Optional": null}, {"Class of": "2018", "Admission Decision": "Accepted", "GPA": "3", "SAT Single": "", "ACT": "26", "Major": "Communication", "AP/IB/Coll": "0", "Honors": "3", "App Deadline": "EA", "Home State": "NJ", "Applied Test Optional": null}, {"Class of": "2017", "Admission Decision": "Accepted", "GPA": "3.96", "SAT Single": "", "ACT": "", "Major": "Engineering - Chemical", "AP/IB/Coll": "18", "Honors": "10", "App Deadline": "EA", "Home State": "CA", "Applied Test Optional": null}, {"Class of": "2019", "Admission Decision": "Accepted", "GPA": "3.23", "SAT Single": "", "ACT": "26", "Major": "Nursing", "AP/IB/Coll": "2", "Honors": "4", "App Deadline": "EA", "Home State": "CA", "Applied Test Optional": null}, {"Class of": "2019", "Admission Decision": "Accepted", "GPA": "3", "SAT Single": 1330, "ACT": "", "Major": "", "AP/IB/Coll": "12", "Honors": "10", "App Deadline": "", "Home State": "CA", "Applied Test Optional": null}, {"Class of": "2017", "Admission Decision": "Accepted", "GPA": "4", "SAT Single": "", "ACT": "", "Major": "Business", "AP/IB/Coll": "18", "Honors": "20", "App Deadline": "", "Home State": "NJ", "Applied Test Optional": null}, {"Class of": "2016", "Admission Decision": "Accepted", "GPA": "2.8", "SAT Single": "", "ACT": "", "Major": "", "AP/IB/Coll": "", "Honors": "", "App Deadline": "", "Home State": "CT", "Applied Test Optional": null}, {"Class of": "2019", "Admission Decision": "Accepted", "GPA": "3.75", "SAT Single": 1450, "ACT": "", "Major": "Political Science", "AP/IB/Coll": "12", "Honors": "6", "App Deadline": "EA", "Home State": "MI", "Applied Test Optional": null}, {"Class of": "2020", "Admission Decision": "Accepted", "GPA": "3.92", "SAT Single": 1560, "ACT": "", "Major": "Computer Science", "AP/IB/Coll": "24", "Honors": "14", "App Deadline": "EA", "Home State": "CA", "Applied Test Optional": null}, {"Class of": "2020", "Admission Decision": "Accepted", "GPA": "4", "SAT Single": "", "ACT": "35", "Major": "Biology - Biochemistry & Molecular", "AP/IB/Coll": "26", "Honors": "2", "App Deadline": "EA", "Home State": "MI", "Applied Test Optional": null}, {"Class of": "2020", "Admission Decision": "Accepted", "GPA": "3.26", "SAT Single": "", "ACT": "27", "Major": "Accounting", "AP/IB/Coll": "10", "Honors": "10", "App Deadline": "EA", "Home State": "CA", "Applied Test Optional": null}, {"Class of": "2020", "Admission Decision": "Accepted", "GPA": "3.66", "SAT Single": "", "ACT": "31", "Major": "Business - Marketing", "AP/IB/Coll": "10", "Honors": "", "App Deadline": "EA", "Home State": "CA", "Applied Test Optional": null}, {"Class of": "2020", "Admission Decision": "__ Not reported", "GPA": "3.16", "SAT Single": "", "ACT": "28", "Major": "Undecided", "AP/IB/Coll": "0", "Honors": "0", "App Deadline": "EA", "Home State": "TX", "Applied Test Optional": null}, {"Class of": "2020", "Admission Decision": "Accepted", "GPA": "3.31", "SAT Single": "", "ACT": "29", "Major": "Environmental Science", "AP/IB/Coll": "8", "Honors": "", "App Deadline": "EA", "Home State": "CA", "Applied Test Optional": null}, {"Class of": "2020", "Admission Decision": "Accepted", "GPA": "", "SAT Single": "", "ACT": "26", "Major": "Undecided", "AP/IB/Coll": "0", "Honors": "4", "App Deadline": "", "Home State": "MI", "Applied Test Optional": null}, {"Class of": "2020", "Admission Decision": "Accepted", "GPA": "3.9", "SAT Single": "", "ACT": "26", "Major": "Undecided", "AP/IB/Coll": "8", "Honors": "16", "App Deadline": "EA", "Home State": "CA", "Applied Test Optional": null}, {"Class of": "2020", "Admission Decision": "Accepted", "GPA": "", "SAT Single": 1490, "ACT": "", "Major": "Biology", "AP/IB/Coll": "16", "Honors": "20", "App Deadline": "EA", "Home State": "CA", "Applied Test Optional": null}, {"Class of": "2020", "Admission Decision": "Accepted", "GPA": "3.36", "SAT Single": "", "ACT": "31", "Major": "Environmental Science", "AP/IB/Coll": "14", "Honors": "10", "App Deadline": "EA", "Home State": "CA", "Applied Test Optional": null}, {"Class of": "2020", "Admission Decision": "Accepted", "GPA": "3.72", "SAT Single": "", "ACT": "31", "Major": "English", "AP/IB/Coll": "6", "Honors": "2", "App Deadline": "EA", "Home State": "CA", "Applied Test Optional": null}, {"Class of": "2020", "Admission Decision": "Accepted", "GPA": "3.38", "SAT Single": 1260, "ACT": "", "Major": "Communication", "AP/IB/Coll": "6", "Honors": "8", "App Deadline": "EA", "Home State": "CA", "Applied Test Optional": null}, {"Class of": "2020", "Admission Decision": "Accepted", "GPA": "2.7", "SAT Single": 1200, "ACT": "", "Major": "Psychology", "AP/IB/Coll": "4", "Honors": "2", "App Deadline": "", "Home State": "CT", "Applied Test Optional": null}, {"Class of": "2020", "Admission Decision": "Accepted", "GPA": "3.5", "SAT Single": 1330, "ACT": "", "Major": "Business - Finance", "AP/IB/Coll": "11", "Honors": "16", "App Deadline": "EA", "Home State": "CA", "Applied Test Optional": null}, {"Class of": "2020", "Admission Decision": "Accepted", "GPA": "3.68", "SAT Single": "", "ACT": "29", "Major": "Business", "AP/IB/Coll": "12", "Honors": "", "App Deadline": "EA", "Home State": "CA", "Applied Test Optional": null}, {"Class of": "2020", "Admission Decision": "Accepted", "GPA": "3.58", "SAT Single": "", "ACT": "25", "Major": "Psychology", "AP/IB/Coll": "8", "Honors": "4", "App Deadline": "", "Home State": "CA", "Applied Test Optional": null}, {"Class of": "2020", "Admission Decision": "Accepted", "GPA": "3.67", "SAT Single": 1400, "ACT": "", "Major": "Engineering", "AP/IB/Coll": "6", "Honors": "6", "App Deadline": "", "Home State": "CA", "Applied Test Optional": null}, {"Class of": "2020", "Admission Decision": "Withdrawn", "GPA": "2.6", "SAT Single": "", "ACT": "23", "Major": "Undecided", "AP/IB/Coll": "0", "Honors": "0", "App Deadline": "EA", "Home State": "NJ", "Applied Test Optional": null}, {"Class of": "2020", "Admission Decision": "Accepted", "GPA": "3.5", "SAT Single": "", "ACT": "28", "Major": "Undecided", "AP/IB/Coll": "4", "Honors": "28", "App Deadline": "", "Home State": "MA", "Applied Test Optional": null}, {"Class of": "2020", "Admission Decision": "Accepted", "GPA": "3.72", "SAT Single": "", "ACT": "32", "Major": "Biology", "AP/IB/Coll": "4", "Honors": "8", "App Deadline": "EA", "Home State": "CA", "Applied Test Optional": null}, {"Class of": "2020", "Admission Decision": "Accepted", "GPA": "3.6", "SAT Single": "", "ACT": "24", "Major": "Undecided", "AP/IB/Coll": "", "Honors": "2", "App Deadline": "EA", "Home State": "CA", "Applied Test Optional": null}, {"Class of": "2020", "Admission Decision": "Accepted", "GPA": "3.74", "SAT Single": 1230, "ACT": "", "Major": "Business - Marketing", "AP/IB/Coll": "6", "Honors": "", "App Deadline": "EA", "Home State": "CA", "Applied Test Optional": null}, {"Class of": "2020", "Admission Decision": "Accepted", "GPA": "3.74", "SAT Single": "", "ACT": "34", "Major": "Psychology", "AP/IB/Coll": "4", "Honors": "2", "App Deadline": "EA", "Home State": "MI", "Applied Test Optional": null}, {"Class of": "2020", "Admission Decision": "Accepted", "GPA": "3.75", "SAT Single": "", "ACT": "33", "Major": "Chemistry", "AP/IB/Coll": "18", "Honors": "16", "App Deadline": "EA", "Home State": "MI", "Applied Test Optional": null}, {"Class of": "2020", "Admission Decision": "Accepted", "GPA": "3", "SAT Single": 1170, "ACT": "22", "Major": "Undecided", "AP/IB/Coll": "4", "Honors": "8", "App Deadline": "EA", "Home State": "CA", "Applied Test Optional": null}, {"Class of": "2020", "Admission Decision": "Accepted", "GPA": "3.68", "SAT Single": 1310, "ACT": "", "Major": "Kinesiology", "AP/IB/Coll": "10", "Honors": "0", "App Deadline": "EA", "Home State": "MI", "Applied Test Optional": null}, {"Class of": "2020", "Admission Decision": "Accepted", "GPA": "2.4", "SAT Single": 1180, "ACT": "", "Major": "Criminology", "AP/IB/Coll": "0", "Honors": "2", "App Deadline": "", "Home State": "MA", "Applied Test Optional": null}, {"Class of": "2020", "Admission Decision": "Accepted", "GPA": "3.13", "SAT Single": 1310, "ACT": "", "Major": "Business", "AP/IB/Coll": "7", "Honors": "4", "App Deadline": "EA", "Home State": "CA", "Applied Test Optional": null}, {"Class of": "2020", "Admission Decision": "Accepted", "GPA": "3.75", "SAT Single": "", "ACT": "33", "Major": "Fisheries And Wildlife Studies", "AP/IB/Coll": "8", "Honors": "30", "App Deadline": "EA", "Home State": "NJ", "Applied Test Optional": null}, {"Class of": "2020", "Admission Decision": "Accepted", "GPA": "3.86", "SAT Single": "", "ACT": "32", "Major": "Environmental Science", "AP/IB/Coll": "14", "Honors": "24", "App Deadline": "EA", "Home State": "MD", "Applied Test Optional": null}, {"Class of": "2020", "Admission Decision": "Accepted", "GPA": "3.62", "SAT Single": 1350, "ACT": "", "Major": "Business - Finance", "AP/IB/Coll": "16", "Honors": "10", "App Deadline": "EA", "Home State": "CA", "Applied Test Optional": null}, {"Class of": "2020", "Admission Decision": "Accepted", "GPA": "3.95", "SAT Single": 1540, "ACT": "", "Major": "Computer Science", "AP/IB/Coll": "18", "Honors": "22", "App Deadline": "EA", "Home State": "VA", "Applied Test Optional": null}, {"Class of": "2020", "Admission Decision": "Accepted", "GPA": "3.4", "SAT Single": "", "ACT": "30", "Major": "Business", "AP/IB/Coll": "14", "Honors": "13", "App Deadline": "EA", "Home State": "CA", "Applied Test Optional": null}, {"Class of": "2020", "Admission Decision": "Accepted", "GPA": "3.77", "SAT Single": 1530, "ACT": "", "Major": "History", "AP/IB/Coll": "10", "Honors": "12", "App Deadline": "EA", "Home State": "MA", "Applied Test Optional": null}, {"Class of": "2020", "Admission Decision": "Accepted", "GPA": "3.36", "SAT Single": "", "ACT": "26", "Major": "Undecided", "AP/IB/Coll": "12", "Honors": "6", "App Deadline": "", "Home State": "CA", "Applied Test Optional": null}, {"Class of": "2020", "Admission Decision": "Accepted", "GPA": "", "SAT Single": 1290, "ACT": "", "Major": "Pre-Med", "AP/IB/Coll": "12", "Honors": "2", "App Deadline": "EA", "Home State": "CA", "Applied Test Optional": null}, {"Class of": "2020", "Admission Decision": "Accepted", "GPA": "3.7", "SAT Single": 1490, "ACT": "", "Major": "Business", "AP/IB/Coll": "30", "Honors": "", "App Deadline": "", "Home State": "MI", "Applied Test Optional": null}, {"Class of": "2020", "Admission Decision": "Accepted", "GPA": "3.14", "SAT Single": "", "ACT": "22", "Major": "Psychology", "AP/IB/Coll": "6", "Honors": "0", "App Deadline": "", "Home State": "CA", "Applied Test Optional": null}, {"Class of": "2020", "Admission Decision": "Accepted", "GPA": "3.77", "SAT Single": "", "ACT": "33", "Major": "Engineering - Mechanical", "AP/IB/Coll": "24", "Honors": "6", "App Deadline": "EA", "Home State": "CA", "Applied Test Optional": null}, {"Class of": "2020", "Admission Decision": "Accepted", "GPA": "2.82", "SAT Single": "", "ACT": "28", "Major": "Business - Sports Management", "AP/IB/Coll": "8", "Honors": "6", "App Deadline": "EA", "Home State": "CA", "Applied Test Optional": null}, {"Class of": "2020", "Admission Decision": "Accepted", "GPA": "3.72", "SAT Single": 1160, "ACT": "", "Major": "Psychology", "AP/IB/Coll": "0", "Honors": "6", "App Deadline": "EA", "Home State": "MI", "Applied Test Optional": null}, {"Class of": "2020", "Admission Decision": "Accepted", "GPA": "3", "SAT Single": 1300, "ACT": "", "Major": "Biology", "AP/IB/Coll": "16", "Honors": "16", "App Deadline": "EA", "Home State": "MD", "Applied Test Optional": null}, {"Class of": "2020", "Admission Decision": "Accepted", "GPA": "3.29", "SAT Single": "", "ACT": "31", "Major": "Computer Science", "AP/IB/Coll": "12", "Honors": "12", "App Deadline": "EA", "Home State": "CA", "Applied Test Optional": null}, {"Class of": "2020", "Admission Decision": "Accepted", "GPA": "4", "SAT Single": 1440, "ACT": "", "Major": "Public Policy", "AP/IB/Coll": "22", "Honors": "12", "App Deadline": "EA", "Home State": "MI", "Applied Test Optional": null}, {"Class of": "2020", "Admission Decision": "Accepted", "GPA": "4", "SAT Single": "", "ACT": "35", "Major": "Engineering - Biomedical", "AP/IB/Coll": "19", "Honors": "23", "App Deadline": "EA", "Home State": "CA", "Applied Test Optional": null}, {"Class of": "2020", "Admission Decision": "Accepted", "GPA": "2.7", "SAT Single": "", "ACT": "19", "Major": "Undecided", "AP/IB/Coll": "4", "Honors": "8", "App Deadline": "EA", "Home State": "NJ", "Applied Test Optional": null}, {"Class of": "2020", "Admission Decision": "Accepted", "GPA": "3.78", "SAT Single": 1230, "ACT": "", "Major": "Engineering - Chemical", "AP/IB/Coll": "0", "Honors": "0", "App Deadline": "EA", "Home State": "MI", "Applied Test Optional": null}, {"Class of": "2020", "Admission Decision": "Accepted", "GPA": "3.6", "SAT Single": "", "ACT": "27", "Major": "", "AP/IB/Coll": "", "Honors": "", "App Deadline": "", "Home State": "CA", "Applied Test Optional": null}, {"Class of": "2020", "Admission Decision": "Accepted", "GPA": "4", "SAT Single": "", "ACT": "36", "Major": "Business", "AP/IB/Coll": "22", "Honors": "12", "App Deadline": "EA", "Home State": "MI", "Applied Test Optional": null}, {"Class of": "2020", "Admission Decision": "Accepted", "GPA": "3.74", "SAT Single": 1430, "ACT": "", "Major": "Business - Finance", "AP/IB/Coll": "14", "Honors": "14", "App Deadline": "EA", "Home State": "MI", "Applied Test Optional": null}, {"Class of": "2020", "Admission Decision": "Accepted", "GPA": "3.88", "SAT Single": "", "ACT": "25", "Major": "Biology", "AP/IB/Coll": "9", "Honors": "14", "App Deadline": "EA", "Home State": "NC", "Applied Test Optional": null}, {"Class of": "2020", "Admission Decision": "Accepted", "GPA": "4", "SAT Single": "", "ACT": "36", "Major": "Engineering - Mechanical", "AP/IB/Coll": "24", "Honors": "8", "App Deadline": "EA", "Home State": "CA", "Applied Test Optional": null}, {"Class of": "2020", "Admission Decision": "Accepted", "GPA": "3.17", "SAT Single": 1500, "ACT": "", "Major": "Engineering - Civil", "AP/IB/Coll": "14", "Honors": "4", "App Deadline": "", "Home State": "CA", "Applied Test Optional": null}, {"Class of": "2020", "Admission Decision": "Accepted", "GPA": "3", "SAT Single": 1360, "ACT": "", "Major": "Biology", "AP/IB/Coll": "8", "Honors": "2", "App Deadline": "", "Home State": "CA", "Applied Test Optional": null}, {"Class of": "2020", "Admission Decision": "Accepted", "GPA": "3.66", "SAT Single": 1350, "ACT": "", "Major": "Computer Science", "AP/IB/Coll": "8", "Honors": "4", "App Deadline": "", "Home State": "CA", "Applied Test Optional": null}, {"Class of": "2020", "Admission Decision": "Accepted", "GPA": "3.31", "SAT Single": "", "ACT": "26", "Major": "Business - Management", "AP/IB/Coll": "0", "Honors": "0", "App Deadline": "EA", "Home State": "CA", "Applied Test Optional": null}, {"Class of": "2020", "Admission Decision": "Accepted", "GPA": "3.94", "SAT Single": "", "ACT": "28", "Major": "Psychology", "AP/IB/Coll": "2", "Honors": "", "App Deadline": "EA", "Home State": "NY", "Applied Test Optional": null}, {"Class of": "2021", "Admission Decision": "Accepted", "GPA": "3.64", "Applied Test Optional": true, "SAT Single": "", "ACT": "", "Major": "Business", "AP/IB/Coll": "5", "Honors": "0", "App Deadline": "EA", "Home State": "CA"}, {"Class of": "2021", "Admission Decision": "Accepted", "GPA": "3.95", "Applied Test Optional": true, "SAT Single": "", "ACT": "", "Major": "Business", "AP/IB/Coll": "10", "Honors": "4", "App Deadline": "EA", "Home State": "CA"}, {"Class of": "2021", "Admission Decision": "Accepted", "GPA": "3.52", "Applied Test Optional": true, "SAT Single": "", "ACT": "", "Major": "Sociology", "AP/IB/Coll": "5", "Honors": "0", "App Deadline": "EA", "Home State": "CA"}, {"Class of": "2021", "Admission Decision": "Accepted", "GPA": "4", "Applied Test Optional": true, "SAT Single": "", "ACT": "", "Major": "Engineering - Chemical", "AP/IB/Coll": "14", "Honors": "2", "App Deadline": "EA", "Home State": "WA"}, {"Class of": "2021", "Admission Decision": "Accepted", "GPA": "4", "Applied Test Optional": false, "SAT Single": 1380, "ACT": "", "Major": "Chemistry", "AP/IB/Coll": "14", "Honors": "16", "App Deadline": "EA", "Home State": "CA"}, {"Class of": "2021", "Admission Decision": "Accepted", "GPA": "3.47", "Applied Test Optional": true, "SAT Single": "", "ACT": "", "Major": "Business", "AP/IB/Coll": "0", "Honors": "0", "App Deadline": "", "Home State": "CA"}, {"Class of": "2021", "Admission Decision": "Accepted", "GPA": "3.18", "Applied Test Optional": false, "SAT Single": "", "ACT": "24", "Major": "Undecided", "AP/IB/Coll": "2", "Honors": "2", "App Deadline": "", "Home State": "CA"}, {"Class of": "2021", "Admission Decision": "Accepted", "GPA": "4", "Applied Test Optional": false, "SAT Single": "", "ACT": "", "Major": "Veterinary Medicine", "AP/IB/Coll": "14", "Honors": "10", "App Deadline": "EA", "Home State": "CA"}, {"Class of": "2021", "Admission Decision": "Accepted", "GPA": "4", "Applied Test Optional": false, "SAT Single": 1190, "ACT": "", "Major": "Engineering Biomedical", "AP/IB/Coll": "0", "Honors": "0", "App Deadline": "EA", "Home State": "IL"}, {"Class of": "2021", "Admission Decision": "Accepted", "GPA": "3.53", "Applied Test Optional": true, "SAT Single": "", "ACT": "", "Major": "Finance", "AP/IB/Coll": "0", "Honors": "8", "App Deadline": "EA", "Home State": ""}, {"Class of": "2021", "Admission Decision": "Accepted", "GPA": "3.43", "Applied Test Optional": false, "SAT Single": 1310, "ACT": "28", "Major": "Math", "AP/IB/Coll": "2", "Honors": "18", "App Deadline": "EA", "Home State": "TX"}, {"Class of": "2021", "Admission Decision": "Accepted", "GPA": "3.8", "Applied Test Optional": false, "SAT Single": 1310, "ACT": "27", "Major": "Computer Science", "AP/IB/Coll": "16", "Honors": "22", "App Deadline": "", "Home State": "TX"}, {"Class of": "2021", "Admission Decision": "Accepted", "GPA": "3.25", "Applied Test Optional": false, "SAT Single": "", "ACT": "32", "Major": "Engineering - Electrical", "AP/IB/Coll": "10", "Honors": "10", "App Deadline": "EA", "Home State": "CA"}, {"Class of": "2021", "Admission Decision": "Accepted", "GPA": "3.88", "Applied Test Optional": true, "SAT Single": "", "ACT": "", "Major": "Political Science", "AP/IB/Coll": "16", "Honors": "6", "App Deadline": "EA", "Home State": "CA"}, {"Class of": "2021", "Admission Decision": "Accepted", "GPA": "3.54", "Applied Test Optional": true, "SAT Single": "", "ACT": "", "Major": "Psychology", "AP/IB/Coll": "0", "Honors": "2", "App Deadline": "EA", "Home State": "CA"}, {"Class of": "2021", "Admission Decision": "Accepted", "GPA": "2.92", "Applied Test Optional": true, "SAT Single": "", "ACT": "", "Major": "Supply Chain Management", "AP/IB/Coll": "0", "Honors": "0", "App Deadline": "", "Home State": "NJ"}, {"Class of": "2021", "Admission Decision": "Accepted", "GPA": "3.71", "Applied Test Optional": true, "SAT Single": "", "ACT": "", "Major": "Interior Design", "AP/IB/Coll": "0", "Honors": "8", "App Deadline": "EA", "Home State": "NJ"}, {"Class of": "2021", "Admission Decision": "Accepted", "GPA": "3.7", "Applied Test Optional": false, "SAT Single": "", "ACT": "", "Major": "Biological Sciences", "AP/IB/Coll": "12", "Honors": "12", "App Deadline": "EA", "Home State": "CA"}, {"Class of": "2021", "Admission Decision": "Accepted", "GPA": "3.23", "Applied Test Optional": true, "SAT Single": "", "ACT": "", "Major": "Engineering - Electrical", "AP/IB/Coll": "8", "Honors": "8", "App Deadline": "", "Home State": "CA"}, {"Class of": "2021", "Admission Decision": "Accepted", "GPA": "3.19", "Applied Test Optional": true, "SAT Single": "", "ACT": "", "Major": "Interior Design", "AP/IB/Coll": "8", "Honors": "", "App Deadline": "EA", "Home State": "CA"}, {"Class of": "2021", "Admission Decision": "Accepted", "GPA": "3.64", "Applied Test Optional": true, "SAT Single": "", "ACT": "22", "Major": "Political Science", "AP/IB/Coll": "14", "Honors": "12", "App Deadline": "EA", "Home State": "IL"}, {"Class of": "2021", "Admission Decision": "Accepted", "GPA": "3.5", "Applied Test Optional": true, "SAT Single": "", "ACT": "", "Major": "Business", "AP/IB/Coll": "16", "Honors": "8", "App Deadline": "", "Home State": "CA"}, {"Class of": "2021", "Admission Decision": "Accepted", "GPA": "3.8", "Applied Test Optional": true, "SAT Single": "", "ACT": "", "Major": "Communication", "AP/IB/Coll": "0", "Honors": "4", "App Deadline": "", "Home State": "NY"}, {"Class of": "2021", "Admission Decision": "Accepted", "GPA": "2.4", "Applied Test Optional": true, "SAT Single": "", "ACT": "", "Major": "Economics", "AP/IB/Coll": "2", "Honors": "0", "App Deadline": "EA", "Home State": "NJ"}, {"Class of": "2021", "Admission Decision": "Accepted", "GPA": "3.95", "Applied Test Optional": true, "SAT Single": "", "ACT": "", "Major": "Biology", "AP/IB/Coll": "16", "Honors": "14", "App Deadline": "", "Home State": "MI"}, {"Class of": "2021", "Admission Decision": "Accepted", "GPA": "3.75", "Applied Test Optional": true, "SAT Single": 1090, "ACT": "", "Major": "Biological Sciences", "AP/IB/Coll": "5", "Honors": "14", "App Deadline": "EA", "Home State": "FL"}, {"Class of": "2021", "Admission Decision": "Accepted", "GPA": "3.22", "Applied Test Optional": true, "SAT Single": "", "ACT": "", "Major": "English", "AP/IB/Coll": "10", "Honors": "", "App Deadline": "EA", "Home State": "WA"}, {"Class of": "2021", "Admission Decision": "Accepted", "GPA": "3.45", "Applied Test Optional": true, "SAT Single": "", "ACT": "", "Major": "Business - Management", "AP/IB/Coll": "10", "Honors": "10", "App Deadline": "EA", "Home State": "CA"}, {"Class of": "2021", "Admission Decision": "Accepted", "GPA": "3.8", "Applied Test Optional": false, "SAT Single": "", "ACT": "27", "Major": "Hotel, Restaurant, Tourism", "AP/IB/Coll": "8", "Honors": "10", "App Deadline": "EA", "Home State": "NJ"}, {"Class of": "2021", "Admission Decision": "Accepted", "GPA": "3.8", "Applied Test Optional": true, "SAT Single": "", "ACT": "", "Major": "Supply Chain Management", "AP/IB/Coll": "6", "Honors": "2", "App Deadline": "", "Home State": "MI"}, {"Class of": "2021", "Admission Decision": "Accepted", "GPA": "3.9", "Applied Test Optional": true, "SAT Single": "", "ACT": "", "Major": "", "AP/IB/Coll": "6", "Honors": "4", "App Deadline": "", "Home State": "MI"}, {"Class of": "2021", "Admission Decision": "Accepted", "GPA": "3.5", "Applied Test Optional": false, "SAT Single": "", "ACT": "30", "Major": "Communication", "AP/IB/Coll": "", "Honors": "1", "App Deadline": "", "Home State": "MI"}, {"Class of": "2021", "Admission Decision": "Accepted", "GPA": "3.4", "Applied Test Optional": true, "SAT Single": "", "ACT": "22", "Major": "Education - Elementary", "AP/IB/Coll": "", "Honors": "2", "App Deadline": "", "Home State": "MI"}, {"Class of": "2021", "Admission Decision": "Accepted", "GPA": "3.67", "Applied Test Optional": false, "SAT Single": "", "ACT": "28", "Major": "Nursing", "AP/IB/Coll": "2", "Honors": "1", "App Deadline": "", "Home State": "MI"}, {"Class of": "2021", "Admission Decision": "Accepted", "GPA": "3.75", "Applied Test Optional": false, "SAT Single": "", "ACT": "28", "Major": "Advertising Creative", "AP/IB/Coll": "2", "Honors": "5", "App Deadline": "", "Home State": "MI"}, {"Class of": "2021", "Admission Decision": "Accepted", "GPA": "3.6", "Applied Test Optional": false, "SAT Single": "", "ACT": "29", "Major": "Finance", "AP/IB/Coll": "10", "Honors": "8", "App Deadline": "", "Home State": "MI"}, {"Class of": "2021", "Admission Decision": "Deferred", "GPA": "3", "Applied Test Optional": true, "SAT Single": "", "ACT": "", "Major": "Psychology", "AP/IB/Coll": "", "Honors": "", "App Deadline": "", "Home State": "MI"}, {"Class of": "2021", "Admission Decision": "Accepted", "GPA": "3.6", "Applied Test Optional": false, "SAT Single": "", "ACT": "29", "Major": "Finance", "AP/IB/Coll": "16", "Honors": "8", "App Deadline": "", "Home State": "MI"}, {"Class of": "2021", "Admission Decision": "Withdrawn", "GPA": "3.51", "Applied Test Optional": false, "SAT Single": "", "ACT": "26", "Major": "Lyman Briggs", "AP/IB/Coll": "2", "Honors": "2", "App Deadline": "", "Home State": "MI"}, {"Class of": "2021", "Admission Decision": "Not reported", "GPA": "2.4", "Applied Test Optional": false, "SAT Single": "", "ACT": "32", "Major": "Communication", "AP/IB/Coll": "", "Honors": "", "App Deadline": "", "Home State": "MI"}, {"Class of": "2021", "Admission Decision": "Accepted", "GPA": "", "Applied Test Optional": false, "SAT Single": "", "ACT": "", "Major": "Finance", "AP/IB/Coll": "0", "Honors": "12", "App Deadline": "Early Action", "Home State": "NY"}]