[{"Class of": "2019", "Admission Decision": "Accepted", "GPA": "3.75", "SAT Single": 1490, "ACT": "", "Major": "Theater - Acting", "AP/IB/Coll": "18", "Honors": "", "App Deadline": "", "Home State": "CA", "Applied Test Optional": null}, {"Class of": "2019", "Admission Decision": "Not Accepted", "GPA": "3.9", "SAT Single": "", "ACT": "35", "Major": "Computer Science", "AP/IB/Coll": "4", "Honors": "7", "App Deadline": "", "Home State": "CT", "Applied Test Optional": null}, {"Class of": "2019", "Admission Decision": "Waitlisted", "GPA": "4", "SAT Single": "", "ACT": "34", "Major": "Computer Science", "AP/IB/Coll": "16", "Honors": "9", "App Deadline": "", "Home State": "CA", "Applied Test Optional": null}, {"Class of": "2017", "Admission Decision": "Not Accepted", "GPA": "3.13", "SAT Single": 930, "ACT": "", "Major": "Theater - Acting", "AP/IB/Coll": "2", "Honors": "0", "App Deadline": "", "Home State": "NY", "Applied Test Optional": null}, {"Class of": "2019", "Admission Decision": "Waitlisted", "GPA": "4", "SAT Single": "", "ACT": "35", "Major": "Engineering - Environmental", "AP/IB/Coll": "20", "Honors": "26", "App Deadline": "", "Home State": "CA", "Applied Test Optional": null}, {"Class of": "2018", "Admission Decision": "Waitlisted", "GPA": "4", "SAT Single": 1510, "ACT": "35", "Major": "Engineering - Electrical", "AP/IB/Coll": "25", "Honors": "16", "App Deadline": "", "Home State": "TX", "Applied Test Optional": null}, {"Class of": "2018", "Admission Decision": "Waitlisted", "GPA": "4", "SAT Single": "", "ACT": "33", "Major": "Physics", "AP/IB/Coll": "16", "Honors": "14", "App Deadline": "", "Home State": "CA", "Applied Test Optional": null}, {"Class of": "2016", "Admission Decision": "Not Accepted", "GPA": "3.66", "SAT Single": "", "ACT": "", "Major": "Art - Graphic Design", "AP/IB/Coll": "17", "Honors": "4", "App Deadline": "", "Home State": "CA", "Applied Test Optional": null}, {"Class of": "2015", "Admission Decision": "Accepted", "GPA": "4", "SAT Single": "", "ACT": "", "Major": "Political Science", "AP/IB/Coll": "18", "Honors": "6", "App Deadline": "", "Home State": "CA", "Applied Test Optional": null}, {"Class of": "2019", "Admission Decision": "Accepted", "GPA": "4", "SAT Single": 1560, "ACT": "", "Major": "Music - Vocal", "AP/IB/Coll": "21", "Honors": "14", "App Deadline": "", "Home State": "CA", "Applied Test Optional": null}, {"Class of": "2015", "Admission Decision": "Waitlisted", "GPA": "3.9", "SAT Single": 1560, "ACT": "", "Major": "Engineering", "AP/IB/Coll": "10", "Honors": "16", "App Deadline": "", "Home State": "", "Applied Test Optional": null}, {"Class of": "2018", "Admission Decision": "Not Accepted", "GPA": "3.91", "SAT Single": 1490, "ACT": "", "Major": "Architecture", "AP/IB/Coll": "", "Honors": "", "App Deadline": "", "Home State": "NJ", "Applied Test Optional": null}, {"Class of": "2018", "Admission Decision": "Accepted", "GPA": "4", "SAT Single": 1560, "ACT": "", "Major": "Computer Science", "AP/IB/Coll": "10", "Honors": "6", "App Deadline": "ED", "Home State": "NJ", "Applied Test Optional": null}, {"Class of": "2018", "Admission Decision": "Not Accepted", "GPA": "4", "SAT Single": 1490, "ACT": "", "Major": "Computer Science", "AP/IB/Coll": "14", "Honors": "28", "App Deadline": "", "Home State": "TX", "Applied Test Optional": null}, {"Class of": "2018", "Admission Decision": "Accepted", "GPA": "4", "SAT Single": 1560, "ACT": "", "Major": "Math - Applied", "AP/IB/Coll": "28", "Honors": "10", "App Deadline": "", "Home State": "VA", "Applied Test Optional": null}, {"Class of": "2018", "Admission Decision": "Waitlisted", "GPA": "3.68", "SAT Single": 1520, "ACT": "", "Major": "Engineering", "AP/IB/Coll": "23", "Honors": "10", "App Deadline": "", "Home State": "CA", "Applied Test Optional": null}, {"Class of": "2018", "Admission Decision": "Waitlisted", "GPA": "3.91", "SAT Single": 1580, "ACT": "", "Major": "Engineering", "AP/IB/Coll": "22", "Honors": "12", "App Deadline": "", "Home State": "NJ", "Applied Test Optional": null}, {"Class of": "2019", "Admission Decision": "Not Accepted", "GPA": "3.7", "SAT Single": "", "ACT": "35", "Major": "Computer Science", "AP/IB/Coll": "14", "Honors": "10", "App Deadline": "", "Home State": "NY", "Applied Test Optional": null}, {"Class of": "2015", "Admission Decision": "Not Accepted", "GPA": "3.41", "SAT Single": 1460, "ACT": "", "Major": "Engineering - Computer", "AP/IB/Coll": "20", "Honors": "16", "App Deadline": "", "Home State": "CA", "Applied Test Optional": null}, {"Class of": "2018", "Admission Decision": "Not Accepted", "GPA": "4", "SAT Single": 1510, "ACT": "", "Major": "Computer Science", "AP/IB/Coll": "", "Honors": "", "App Deadline": "", "Home State": "", "Applied Test Optional": null}, {"Class of": "2017", "Admission Decision": "Accepted", "GPA": "4", "SAT Single": "", "ACT": "", "Major": "", "AP/IB/Coll": "24", "Honors": "8", "App Deadline": "", "Home State": "CA", "Applied Test Optional": null}, {"Class of": "2018", "Admission Decision": "Waitlisted", "GPA": "3.9", "SAT Single": 1490, "ACT": "", "Major": "Business", "AP/IB/Coll": "12", "Honors": "14", "App Deadline": "", "Home State": "CA", "Applied Test Optional": null}, {"Class of": "2016", "Admission Decision": "Not Accepted", "GPA": "3.7", "SAT Single": "", "ACT": "", "Major": "", "AP/IB/Coll": "2", "Honors": "", "App Deadline": "", "Home State": "", "Applied Test Optional": null}, {"Class of": "2016", "Admission Decision": "Not Accepted", "GPA": "3.79", "SAT Single": 1550, "ACT": "", "Major": "Math", "AP/IB/Coll": "18", "Honors": "16", "App Deadline": "", "Home State": "CA", "Applied Test Optional": null}, {"Class of": "2016", "Admission Decision": "Accepted", "GPA": "3.71", "SAT Single": 1500, "ACT": "", "Major": "", "AP/IB/Coll": "21", "Honors": "21", "App Deadline": "", "Home State": "MA", "Applied Test Optional": null}, {"Class of": "2015", "Admission Decision": "Not Accepted", "GPA": "3.93", "SAT Single": 1380, "ACT": "", "Major": "Computer Science", "AP/IB/Coll": "9", "Honors": "30", "App Deadline": "", "Home State": "MA", "Applied Test Optional": null}, {"Class of": "2017", "Admission Decision": "Not Accepted", "GPA": "3.93", "SAT Single": "", "ACT": "", "Major": "Computer Science", "AP/IB/Coll": "24", "Honors": "16", "App Deadline": "ED", "Home State": "NJ", "Applied Test Optional": null}, {"Class of": "2019", "Admission Decision": "Waitlisted", "GPA": "3.86", "SAT Single": 1520, "ACT": "", "Major": "Math", "AP/IB/Coll": "20", "Honors": "10", "App Deadline": "", "Home State": "CA", "Applied Test Optional": null}, {"Class of": "2015", "Admission Decision": "Accepted", "GPA": "4", "SAT Single": 1530, "ACT": "", "Major": "Physics", "AP/IB/Coll": "24", "Honors": "8", "App Deadline": "", "Home State": "NJ", "Applied Test Optional": null}, {"Class of": "2019", "Admission Decision": "Not Accepted", "GPA": "4", "SAT Single": 1480, "ACT": "", "Major": "Computer Science", "AP/IB/Coll": "20", "Honors": "26", "App Deadline": "", "Home State": "TX", "Applied Test Optional": null}, {"Class of": "2019", "Admission Decision": "Waitlisted", "GPA": "3.77", "SAT Single": 1170, "ACT": "26", "Major": "Theater - Design and Production", "AP/IB/Coll": "6", "Honors": "4", "App Deadline": "EA", "Home State": "CA", "Applied Test Optional": null}, {"Class of": "2018", "Admission Decision": "Accepted", "GPA": "3.74", "SAT Single": 1540, "ACT": "", "Major": "Engineering - Civil", "AP/IB/Coll": "10", "Honors": "28", "App Deadline": "", "Home State": "MA", "Applied Test Optional": null}, {"Class of": "2019", "Admission Decision": "Not Accepted", "GPA": "3.48", "SAT Single": "", "ACT": "25", "Major": "Music - Musical Theatre", "AP/IB/Coll": "0", "Honors": "0", "App Deadline": "EA", "Home State": "WA", "Applied Test Optional": null}, {"Class of": "2018", "Admission Decision": "Not Accepted", "GPA": "3.41", "SAT Single": "", "ACT": "28", "Major": "Theater - Musical", "AP/IB/Coll": "9", "Honors": "4", "App Deadline": "", "Home State": "CA", "Applied Test Optional": null}, {"Class of": "2017", "Admission Decision": "Accepted", "GPA": "3.93", "SAT Single": "", "ACT": "", "Major": "Computer Science", "AP/IB/Coll": "24", "Honors": "16", "App Deadline": "", "Home State": "NJ", "Applied Test Optional": null}, {"Class of": "2018", "Admission Decision": "Not Accepted", "GPA": "3.9", "SAT Single": "", "ACT": "33", "Major": "Engineering - Mechanical", "AP/IB/Coll": "18", "Honors": "10", "App Deadline": "", "Home State": "CA", "Applied Test Optional": null}, {"Class of": "2017", "Admission Decision": "Waitlisted", "GPA": "3.85", "SAT Single": "", "ACT": "", "Major": "Biology", "AP/IB/Coll": "8", "Honors": "9", "App Deadline": "", "Home State": "NJ", "Applied Test Optional": null}, {"Class of": "2017", "Admission Decision": "Waitlisted", "GPA": "3.92", "SAT Single": 1470, "ACT": "", "Major": "Engineering - Mechanical", "AP/IB/Coll": "22", "Honors": "", "App Deadline": "", "Home State": "TX", "Applied Test Optional": null}, {"Class of": "2019", "Admission Decision": "Waitlisted", "GPA": "3.68", "SAT Single": 1500, "ACT": "", "Major": "Business - Administration", "AP/IB/Coll": "14", "Honors": "24", "App Deadline": "", "Home State": "NJ", "Applied Test Optional": null}, {"Class of": "2016", "Admission Decision": "Waitlisted", "GPA": "3.88", "SAT Single": 1370, "ACT": "", "Major": "", "AP/IB/Coll": "16", "Honors": "10", "App Deadline": "", "Home State": "WA", "Applied Test Optional": null}, {"Class of": "2019", "Admission Decision": "Waitlisted", "GPA": "3.55", "SAT Single": 1300, "ACT": "33", "Major": "Biology - Biological Sciences", "AP/IB/Coll": "16", "Honors": "7", "App Deadline": "", "Home State": "CA", "Applied Test Optional": null}, {"Class of": "2017", "Admission Decision": "Not Accepted", "GPA": "4", "SAT Single": 1440, "ACT": "", "Major": "Biology", "AP/IB/Coll": "16", "Honors": "18", "App Deadline": "", "Home State": "MA", "Applied Test Optional": null}, {"Class of": "2017", "Admission Decision": "Waitlisted", "GPA": "4", "SAT Single": "", "ACT": "", "Major": "English", "AP/IB/Coll": "8", "Honors": "26", "App Deadline": "", "Home State": "MA", "Applied Test Optional": null}, {"Class of": "2018", "Admission Decision": "Waitlisted", "GPA": "4", "SAT Single": "", "ACT": "33", "Major": "Music - Performance", "AP/IB/Coll": "10", "Honors": "8", "App Deadline": "", "Home State": "NY", "Applied Test Optional": null}, {"Class of": "2018", "Admission Decision": "Not Accepted", "GPA": "3.23", "SAT Single": 1240, "ACT": "", "Major": "Theater - Musical", "AP/IB/Coll": "6", "Honors": "4", "App Deadline": "", "Home State": "MI", "Applied Test Optional": null}, {"Class of": "2018", "Admission Decision": "Not Accepted", "GPA": "3.79", "SAT Single": 1430, "ACT": "32", "Major": "Computer Science", "AP/IB/Coll": "12", "Honors": "14", "App Deadline": "", "Home State": "NC", "Applied Test Optional": null}, {"Class of": "2016", "Admission Decision": "Waitlisted", "GPA": "3.8", "SAT Single": "", "ACT": "", "Major": "Biology", "AP/IB/Coll": "11", "Honors": "3", "App Deadline": "", "Home State": "TX", "Applied Test Optional": null}, {"Class of": "2018", "Admission Decision": "Not Accepted", "GPA": "4", "SAT Single": "", "ACT": "33", "Major": "Computer Science", "AP/IB/Coll": "16", "Honors": "20", "App Deadline": "ED", "Home State": "TX", "Applied Test Optional": null}, {"Class of": "2019", "Admission Decision": "Not Accepted", "GPA": "3.92", "SAT Single": 1520, "ACT": "", "Major": "Engineering - Aero", "AP/IB/Coll": "20", "Honors": "12", "App Deadline": "", "Home State": "", "Applied Test Optional": null}, {"Class of": "2017", "Admission Decision": "Not Accepted", "GPA": "4", "SAT Single": 1510, "ACT": "", "Major": "Engineering - Electrical", "AP/IB/Coll": "24", "Honors": "12", "App Deadline": "", "Home State": "CA", "Applied Test Optional": null}, {"Class of": "2017", "Admission Decision": "Not Accepted", "GPA": "3.6", "SAT Single": "", "ACT": "", "Major": "Theater - Musical", "AP/IB/Coll": "10", "Honors": "0", "App Deadline": "", "Home State": "CA", "Applied Test Optional": null}, {"Class of": "2018", "Admission Decision": "Accepted", "GPA": "3.52", "SAT Single": 1530, "ACT": "34", "Major": "Business - Administration", "AP/IB/Coll": "22", "Honors": "38", "App Deadline": "", "Home State": "TX", "Applied Test Optional": null}, {"Class of": "2016", "Admission Decision": "Waitlisted", "GPA": "3.65", "SAT Single": 1440, "ACT": "", "Major": "Economics", "AP/IB/Coll": "", "Honors": "", "App Deadline": "", "Home State": "CT", "Applied Test Optional": null}, {"Class of": "2016", "Admission Decision": "Not Accepted", "GPA": "2.92", "SAT Single": 1540, "ACT": "", "Major": "Engineering", "AP/IB/Coll": "20", "Honors": "10", "App Deadline": "", "Home State": "VA", "Applied Test Optional": null}, {"Class of": "2019", "Admission Decision": "Waitlisted then not accepted", "GPA": "3.9", "SAT Single": 1530, "ACT": "", "Major": "Engineering - Mechanical", "AP/IB/Coll": "28", "Honors": "24", "App Deadline": "", "Home State": "MD", "Applied Test Optional": null}, {"Class of": "2018", "Admission Decision": "Accepted", "GPA": "3.84", "SAT Single": "", "ACT": "33", "Major": "Music", "AP/IB/Coll": "20", "Honors": "6", "App Deadline": "", "Home State": "WA", "Applied Test Optional": null}, {"Class of": "2019", "Admission Decision": "Not Accepted", "GPA": "4", "SAT Single": "", "ACT": "35", "Major": "Engineering", "AP/IB/Coll": "10", "Honors": "4", "App Deadline": "", "Home State": "CA", "Applied Test Optional": null}, {"Class of": "2019", "Admission Decision": "Accepted", "GPA": "3.8", "SAT Single": 1550, "ACT": "", "Major": "Computer Science", "AP/IB/Coll": "14", "Honors": "10", "App Deadline": "ED", "Home State": "CA", "Applied Test Optional": null}, {"Class of": "2019", "Admission Decision": "Not Accepted", "GPA": "4", "SAT Single": 1530, "ACT": "34", "Major": "Computer Science", "AP/IB/Coll": "28", "Honors": "12", "App Deadline": "", "Home State": "NJ", "Applied Test Optional": null}, {"Class of": "2016", "Admission Decision": "Accepted", "GPA": "4", "SAT Single": 1290, "ACT": "", "Major": "Math", "AP/IB/Coll": "20", "Honors": "22", "App Deadline": "", "Home State": "NJ", "Applied Test Optional": null}, {"Class of": "2016", "Admission Decision": "Not Accepted", "GPA": "3.65", "SAT Single": "", "ACT": "", "Major": "Engineering - Mechanical", "AP/IB/Coll": "22", "Honors": "4", "App Deadline": "", "Home State": "CA", "Applied Test Optional": null}, {"Class of": "2016", "Admission Decision": "Accepted", "GPA": "3.1", "SAT Single": 1440, "ACT": "", "Major": "Engineering - Chemical", "AP/IB/Coll": "6", "Honors": "31", "App Deadline": "", "Home State": "MA", "Applied Test Optional": null}, {"Class of": "2018", "Admission Decision": "Not Accepted", "GPA": "3.93", "SAT Single": 1540, "ACT": "", "Major": "Engineering", "AP/IB/Coll": "12", "Honors": "", "App Deadline": "", "Home State": "NJ", "Applied Test Optional": null}, {"Class of": "2018", "Admission Decision": "Not Accepted", "GPA": "3.54", "SAT Single": 1470, "ACT": "", "Major": "Engineering - Electrical", "AP/IB/Coll": "10", "Honors": "19", "App Deadline": "", "Home State": "MA", "Applied Test Optional": null}, {"Class of": "2015", "Admission Decision": "Accepted", "GPA": "3.4", "SAT Single": 1230, "ACT": "", "Major": "Product Design", "AP/IB/Coll": "2", "Honors": "", "App Deadline": "", "Home State": "CA", "Applied Test Optional": null}, {"Class of": "2017", "Admission Decision": "Waitlisted", "GPA": "3.82", "SAT Single": "", "ACT": "", "Major": "Computer Science", "AP/IB/Coll": "10", "Honors": "12", "App Deadline": "", "Home State": "CA", "Applied Test Optional": null}, {"Class of": "2017", "Admission Decision": "Not Accepted", "GPA": "3.93", "SAT Single": "", "ACT": "", "Major": "Computer Science", "AP/IB/Coll": "24", "Honors": "16", "App Deadline": "", "Home State": "NJ", "Applied Test Optional": null}, {"Class of": "2016", "Admission Decision": "Waitlisted", "GPA": "3.58", "SAT Single": 1480, "ACT": "", "Major": "Biology", "AP/IB/Coll": "8", "Honors": "14", "App Deadline": "", "Home State": "NJ", "Applied Test Optional": null}, {"Class of": "2018", "Admission Decision": "Not Accepted", "GPA": "3.85", "SAT Single": "", "ACT": "35", "Major": "Computer Science", "AP/IB/Coll": "30", "Honors": "0", "App Deadline": "", "Home State": "WA", "Applied Test Optional": null}, {"Class of": "2018", "Admission Decision": "Not Accepted", "GPA": "3.72", "SAT Single": "", "ACT": "34", "Major": "Computer Science", "AP/IB/Coll": "18", "Honors": "12", "App Deadline": "ED", "Home State": "NJ", "Applied Test Optional": null}, {"Class of": "2019", "Admission Decision": "Accepted", "GPA": "4", "SAT Single": "", "ACT": "33", "Major": "Engineering - Chemical", "AP/IB/Coll": "14", "Honors": "10", "App Deadline": "EA", "Home State": "CA", "Applied Test Optional": null}, {"Class of": "2019", "Admission Decision": "Accepted", "GPA": "3.85", "SAT Single": 1560, "ACT": "", "Major": "Engineering", "AP/IB/Coll": "24", "Honors": "18", "App Deadline": "", "Home State": "CT", "Applied Test Optional": null}, {"Class of": "2018", "Admission Decision": "Not Accepted", "GPA": "4", "SAT Single": 1550, "ACT": "", "Major": "Math - Applied", "AP/IB/Coll": "14", "Honors": "34", "App Deadline": "", "Home State": "NJ", "Applied Test Optional": null}, {"Class of": "2017", "Admission Decision": "Accepted", "GPA": "3.68", "SAT Single": "", "ACT": "", "Major": "Theater", "AP/IB/Coll": "4", "Honors": "2", "App Deadline": "", "Home State": "CA", "Applied Test Optional": null}, {"Class of": "2018", "Admission Decision": "Not Accepted", "GPA": "3.43", "SAT Single": "", "ACT": "34", "Major": "Engineering - Electrical", "AP/IB/Coll": "10", "Honors": "14", "App Deadline": "ED", "Home State": "CT", "Applied Test Optional": null}, {"Class of": "2017", "Admission Decision": "Accepted", "GPA": "4", "SAT Single": 1560, "ACT": "", "Major": "Biology", "AP/IB/Coll": "12", "Honors": "8", "App Deadline": "", "Home State": "CA", "Applied Test Optional": null}, {"Class of": "2017", "Admission Decision": "Accepted", "GPA": "3.95", "SAT Single": 1510, "ACT": "", "Major": "Engineering - Computer", "AP/IB/Coll": "12", "Honors": "6", "App Deadline": "", "Home State": "CA", "Applied Test Optional": null}, {"Class of": "2019", "Admission Decision": "Not Accepted", "GPA": "3.78", "SAT Single": "", "ACT": "34", "Major": "Engineering - Aero", "AP/IB/Coll": "12", "Honors": "14", "App Deadline": "", "Home State": "OH", "Applied Test Optional": null}, {"Class of": "2018", "Admission Decision": "Waitlisted", "GPA": "4", "SAT Single": "", "ACT": "30", "Major": "Engineering - Architectural", "AP/IB/Coll": "24", "Honors": "32", "App Deadline": "", "Home State": "TX", "Applied Test Optional": null}, {"Class of": "2017", "Admission Decision": "Waitlisted", "GPA": "3.8", "SAT Single": 1510, "ACT": "", "Major": "", "AP/IB/Coll": "6", "Honors": "26", "App Deadline": "", "Home State": "MA", "Applied Test Optional": null}, {"Class of": "2015", "Admission Decision": "Waitlisted", "GPA": "4", "SAT Single": 1530, "ACT": "", "Major": "Computer Science", "AP/IB/Coll": "24", "Honors": "8", "App Deadline": "", "Home State": "NJ", "Applied Test Optional": null}, {"Class of": "2017", "Admission Decision": "Accepted", "GPA": "3.92", "SAT Single": 1580, "ACT": "", "Major": "", "AP/IB/Coll": "18", "Honors": "23", "App Deadline": "", "Home State": "MA", "Applied Test Optional": null}, {"Class of": "2016", "Admission Decision": "Waitlisted", "GPA": "3.5", "SAT Single": 1600, "ACT": "", "Major": "Business - Economics", "AP/IB/Coll": "4", "Honors": "7", "App Deadline": "", "Home State": "NJ", "Applied Test Optional": null}, {"Class of": "2018", "Admission Decision": "Not Accepted", "GPA": "3.5", "SAT Single": "", "ACT": "33", "Major": "Engineering - Chemical", "AP/IB/Coll": "8", "Honors": "14", "App Deadline": "", "Home State": "CA", "Applied Test Optional": null}, {"Class of": "2015", "Admission Decision": "Waitlisted", "GPA": "3.85", "SAT Single": 1550, "ACT": "", "Major": "Engineering", "AP/IB/Coll": "14", "Honors": "20", "App Deadline": "", "Home State": "", "Applied Test Optional": null}, {"Class of": "2017", "Admission Decision": "Not Accepted", "GPA": "3.45", "SAT Single": "", "ACT": "", "Major": "Engineering - Biomedical", "AP/IB/Coll": "10", "Honors": "10", "App Deadline": "", "Home State": "CA", "Applied Test Optional": null}, {"Class of": "2015", "Admission Decision": "Not Accepted", "GPA": "3.37", "SAT Single": 1550, "ACT": "", "Major": "Engineering - Undecided", "AP/IB/Coll": "10", "Honors": "12", "App Deadline": "", "Home State": "MA", "Applied Test Optional": null}, {"Class of": "2018", "Admission Decision": "Not Accepted", "GPA": "3.57", "SAT Single": 1560, "ACT": "35", "Major": "Engineering - Electrical", "AP/IB/Coll": "20", "Honors": "12", "App Deadline": "", "Home State": "NJ", "Applied Test Optional": null}, {"Class of": "2017", "Admission Decision": "Accepted", "GPA": "3.65", "SAT Single": 1440, "ACT": "", "Major": "Engineering", "AP/IB/Coll": "21", "Honors": "8", "App Deadline": "", "Home State": "CA", "Applied Test Optional": null}, {"Class of": "2020", "Admission Decision": "Not Accepted", "GPA": "4", "SAT Single": 1530, "ACT": "", "Major": "Engineering - Biochemical", "AP/IB/Coll": "18", "Honors": "16", "App Deadline": "ED", "Home State": "NJ", "Applied Test Optional": null}, {"Class of": "2020", "Admission Decision": "__ Not reported", "GPA": "3.82", "SAT Single": "", "ACT": "29", "Major": "Engineering - Computer", "AP/IB/Coll": "24", "Honors": "16", "App Deadline": "", "Home State": "TX", "Applied Test Optional": null}, {"Class of": "2020", "Admission Decision": "Withdrawn", "GPA": "3.7", "SAT Single": "", "ACT": "35", "Major": "", "AP/IB/Coll": "10", "Honors": "4", "App Deadline": "", "Home State": "NJ", "Applied Test Optional": null}, {"Class of": "2020", "Admission Decision": "Waitlisted", "GPA": "3.7", "SAT Single": 1490, "ACT": "", "Major": "Engineering - Civil", "AP/IB/Coll": "12", "Honors": "16", "App Deadline": "", "Home State": "VA", "Applied Test Optional": null}, {"Class of": "2020", "Admission Decision": "Accepted", "GPA": "3.9", "SAT Single": 1510, "ACT": "", "Major": "Engineering - Mechanical", "AP/IB/Coll": "10", "Honors": "22", "App Deadline": "", "Home State": "NY", "Applied Test Optional": null}, {"Class of": "2020", "Admission Decision": "Deferred\u00a0then\u00a0accepted", "GPA": "3.6", "SAT Single": 1480, "ACT": "34", "Major": "Engineering - Mechanical", "AP/IB/Coll": "19", "Honors": "16", "App Deadline": "ED", "Home State": "CT", "Applied Test Optional": null}, {"Class of": "2020", "Admission Decision": "Accepted", "GPA": "3.6", "SAT Single": 1450, "ACT": "35", "Major": "Business", "AP/IB/Coll": "20", "Honors": "17", "App Deadline": "ED", "Home State": "NJ", "Applied Test Optional": null}, {"Class of": "2020", "Admission Decision": "Not Accepted", "GPA": "3.8", "SAT Single": 1530, "ACT": "", "Major": "Engineering - Electrical", "AP/IB/Coll": "14", "Honors": "20", "App Deadline": "", "Home State": "MA", "Applied Test Optional": null}, {"Class of": "2020", "Admission Decision": "Waitlisted", "GPA": "4", "SAT Single": 1580, "ACT": "36", "Major": "Math - Statistics", "AP/IB/Coll": "24", "Honors": "22", "App Deadline": "", "Home State": "NJ", "Applied Test Optional": null}, {"Class of": "2020", "Admission Decision": "Accepted", "GPA": "3.68", "SAT Single": 1500, "ACT": "", "Major": "Business", "AP/IB/Coll": "13", "Honors": "4", "App Deadline": "ED", "Home State": "CA", "Applied Test Optional": null}, {"Class of": "2020", "Admission Decision": "Not Accepted", "GPA": "3.7", "SAT Single": 1490, "ACT": "", "Major": "Business", "AP/IB/Coll": "30", "Honors": "", "App Deadline": "", "Home State": "MI", "Applied Test Optional": null}, {"Class of": "2020", "Admission Decision": "Accepted", "GPA": "3.5", "SAT Single": 1440, "ACT": "", "Major": "Math", "AP/IB/Coll": "16", "Honors": "16", "App Deadline": "ED", "Home State": "VA", "Applied Test Optional": null}, {"Class of": "2020", "Admission Decision": "Not Accepted", "GPA": "3.54", "SAT Single": 1510, "ACT": "", "Major": "Computer Science", "AP/IB/Coll": "12", "Honors": "6", "App Deadline": "ED", "Home State": "CA", "Applied Test Optional": null}, {"Class of": "2020", "Admission Decision": "__ Not reported", "GPA": "4", "SAT Single": 1600, "ACT": "", "Major": "Computer Science", "AP/IB/Coll": "28", "Honors": "10", "App Deadline": "", "Home State": "CA", "Applied Test Optional": null}, {"Class of": "2020", "Admission Decision": "Not Accepted", "GPA": "3.94", "SAT Single": "", "ACT": "35", "Major": "Engineering - Mechanical", "AP/IB/Coll": "16", "Honors": "14", "App Deadline": "", "Home State": "CA", "Applied Test Optional": null}, {"Class of": "2020", "Admission Decision": "Not Accepted", "GPA": "4", "SAT Single": 1440, "ACT": "", "Major": "Engineering", "AP/IB/Coll": "", "Honors": "", "App Deadline": "", "Home State": "CA", "Applied Test Optional": null}, {"Class of": "2020", "Admission Decision": "Waitlisted", "GPA": "3.91", "SAT Single": "", "ACT": "31", "Major": "Chemistry", "AP/IB/Coll": "12", "Honors": "14", "App Deadline": "", "Home State": "CA", "Applied Test Optional": null}, {"Class of": "2020", "Admission Decision": "Not Accepted", "GPA": "3.56", "SAT Single": 1490, "ACT": "", "Major": "Biology - Computational Biology", "AP/IB/Coll": "12", "Honors": "8", "App Deadline": "EA", "Home State": "ME", "Applied Test Optional": null}, {"Class of": "2020", "Admission Decision": "Waitlisted", "GPA": "3.96", "SAT Single": 1580, "ACT": "36", "Major": "Computer Science", "AP/IB/Coll": "18", "Honors": "20", "App Deadline": "", "Home State": "CA", "Applied Test Optional": null}, {"Class of": "2020", "Admission Decision": "Not Accepted", "GPA": "4", "SAT Single": 1540, "ACT": "35", "Major": "Engineering - Computer", "AP/IB/Coll": "14", "Honors": "20", "App Deadline": "", "Home State": "CA", "Applied Test Optional": null}, {"Class of": "2020", "Admission Decision": "Waitlisted", "GPA": "3.8", "SAT Single": "", "ACT": "35", "Major": "Anthropology", "AP/IB/Coll": "18", "Honors": "18", "App Deadline": "", "Home State": "GA", "Applied Test Optional": null}, {"Class of": "2020", "Admission Decision": "Accepted", "GPA": "3.84", "SAT Single": "", "ACT": "34", "Major": "Math - Statistics", "AP/IB/Coll": "18", "Honors": "1", "App Deadline": "ED", "Home State": "NY", "Applied Test Optional": null}, {"Class of": "2020", "Admission Decision": "Withdrawn", "GPA": "4", "SAT Single": 1550, "ACT": "", "Major": "Computer Science", "AP/IB/Coll": "23", "Honors": "8", "App Deadline": "", "Home State": "TX", "Applied Test Optional": null}, {"Class of": "2020", "Admission Decision": "Not Accepted", "GPA": "3.6", "SAT Single": 1440, "ACT": "", "Major": "Computer Science", "AP/IB/Coll": "10", "Honors": "20", "App Deadline": "", "Home State": "CT", "Applied Test Optional": null}, {"Class of": "2020", "Admission Decision": "Waitlisted", "GPA": "3.94", "SAT Single": 1600, "ACT": "36", "Major": "Computer Science", "AP/IB/Coll": "24", "Honors": "18", "App Deadline": "", "Home State": "CO", "Applied Test Optional": null}, {"Class of": "2020", "Admission Decision": "Not Accepted", "GPA": "3.92", "SAT Single": 1560, "ACT": "", "Major": "Computer Science", "AP/IB/Coll": "24", "Honors": "14", "App Deadline": "", "Home State": "CA", "Applied Test Optional": null}, {"Class of": "2020", "Admission Decision": "Withdrawn", "GPA": "3.91", "SAT Single": 1530, "ACT": "", "Major": "Math", "AP/IB/Coll": "2", "Honors": "6", "App Deadline": "", "Home State": "", "Applied Test Optional": null}, {"Class of": "2020", "Admission Decision": "Not Accepted", "GPA": "4", "SAT Single": "", "ACT": "34", "Major": "Engineering - Electrical", "AP/IB/Coll": "8", "Honors": "4", "App Deadline": "", "Home State": "MI", "Applied Test Optional": null}, {"Class of": "2020", "Admission Decision": "Waitlisted", "GPA": "3.86", "SAT Single": "", "ACT": "35", "Major": "Engineering", "AP/IB/Coll": "20", "Honors": "2", "App Deadline": "", "Home State": "NJ", "Applied Test Optional": null}, {"Class of": "2020", "Admission Decision": "Not Accepted", "GPA": "3.96", "SAT Single": 1570, "ACT": "", "Major": "Computer Science", "AP/IB/Coll": "16", "Honors": "18", "App Deadline": "", "Home State": "CA", "Applied Test Optional": null}, {"Class of": "2020", "Admission Decision": "Accepted", "GPA": "3.93", "SAT Single": 1430, "ACT": "", "Major": "Biology", "AP/IB/Coll": "44", "Honors": "2", "App Deadline": "", "Home State": "FL", "Applied Test Optional": null}, {"Class of": "2020", "Admission Decision": "Not Accepted", "GPA": "4", "SAT Single": 1340, "ACT": "", "Major": "Business", "AP/IB/Coll": "16", "Honors": "16", "App Deadline": "", "Home State": "CT", "Applied Test Optional": null}, {"Class of": "2020", "Admission Decision": "Not Accepted", "GPA": "3.86", "SAT Single": "", "ACT": "32", "Major": "Environmental Science", "AP/IB/Coll": "14", "Honors": "24", "App Deadline": "", "Home State": "MD", "Applied Test Optional": null}, {"Class of": "2020", "Admission Decision": "Not Accepted", "GPA": "3.69", "SAT Single": 1270, "ACT": "28", "Major": "Physics", "AP/IB/Coll": "18", "Honors": "8", "App Deadline": "ED", "Home State": "CA", "Applied Test Optional": null}, {"Class of": "2020", "Admission Decision": "Waitlisted", "GPA": "4", "SAT Single": "", "ACT": "34", "Major": "Computer Science", "AP/IB/Coll": "20", "Honors": "20", "App Deadline": "", "Home State": "CA", "Applied Test Optional": null}, {"Class of": "2020", "Admission Decision": "Not Accepted", "GPA": "3.93", "SAT Single": 1580, "ACT": "", "Major": "Computer Science", "AP/IB/Coll": "26", "Honors": "18", "App Deadline": "", "Home State": "TX", "Applied Test Optional": null}, {"Class of": "2020", "Admission Decision": "Waitlisted", "GPA": "4", "SAT Single": "", "ACT": "36", "Major": "Business", "AP/IB/Coll": "22", "Honors": "12", "App Deadline": "", "Home State": "MI", "Applied Test Optional": null}, {"Class of": "2020", "Admission Decision": "Not Accepted", "GPA": "3.74", "SAT Single": 1430, "ACT": "", "Major": "Business - Administration", "AP/IB/Coll": "14", "Honors": "14", "App Deadline": "", "Home State": "MI", "Applied Test Optional": null}, {"Class of": "2020", "Admission Decision": "Not Accepted", "GPA": "3.7", "SAT Single": 1520, "ACT": "", "Major": "Computer Information Systems", "AP/IB/Coll": "18", "Honors": "18", "App Deadline": "ED", "Home State": "CA", "Applied Test Optional": null}, {"Class of": "2021", "Admission Decision": "Not Accepted", "GPA": "3.3", "Applied Test Optional": true, "SAT Single": "", "ACT": "30", "Major": "Engineering", "AP/IB/Coll": "10", "Honors": "10", "App Deadline": "", "Home State": "MD"}, {"Class of": "2021", "Admission Decision": "Not reported", "GPA": "3.9", "Applied Test Optional": false, "SAT Single": "", "ACT": "36", "Major": "Computer Science", "AP/IB/Coll": "20", "Honors": "14", "App Deadline": "", "Home State": "NY"}, {"Class of": "2021", "Admission Decision": "Withdrawn", "GPA": "4", "Applied Test Optional": false, "SAT Single": 1510, "ACT": "", "Major": "Math", "AP/IB/Coll": "18", "Honors": "", "App Deadline": "", "Home State": "VA"}, {"Class of": "2021", "Admission Decision": "Waitlisted", "GPA": "4", "Applied Test Optional": true, "SAT Single": "", "ACT": "", "Major": "Computer Science - Engineering", "AP/IB/Coll": "20", "Honors": "18", "App Deadline": "", "Home State": "CA"}, {"Class of": "2021", "Admission Decision": "Accepted", "GPA": "4", "Applied Test Optional": false, "SAT Single": "", "ACT": "35", "Major": "Economics", "AP/IB/Coll": "30", "Honors": "8", "App Deadline": "", "Home State": "WA"}, {"Class of": "2021", "Admission Decision": "Waitlisted", "GPA": "3.94", "Applied Test Optional": false, "SAT Single": "", "ACT": "34", "Major": "Engineering", "AP/IB/Coll": "24", "Honors": "10", "App Deadline": "", "Home State": "WA"}, {"Class of": "2021", "Admission Decision": "Not reported", "GPA": "4", "Applied Test Optional": true, "SAT Single": 1310, "ACT": "", "Major": "Engineering - Biomedical", "AP/IB/Coll": "4", "Honors": "14", "App Deadline": "", "Home State": "CA"}, {"Class of": "2021", "Admission Decision": "Not reported", "GPA": "4", "Applied Test Optional": false, "SAT Single": "", "ACT": "35", "Major": "Physics", "AP/IB/Coll": "16", "Honors": "4", "App Deadline": "", "Home State": "CA"}, {"Class of": "2021", "Admission Decision": "Not Accepted", "GPA": "3.75", "Applied Test Optional": true, "SAT Single": "", "ACT": "32", "Major": "Computer Science", "AP/IB/Coll": "26", "Honors": "16", "App Deadline": "ED", "Home State": "UT"}, {"Class of": "2021", "Admission Decision": "Not Accepted", "GPA": "3.78", "Applied Test Optional": false, "SAT Single": "", "ACT": "", "Major": "Engineering", "AP/IB/Coll": "24", "Honors": "10", "App Deadline": "", "Home State": ""}, {"Class of": "2021", "Admission Decision": "Not Accepted", "GPA": "3.7", "Applied Test Optional": false, "SAT Single": "", "ACT": "", "Major": "Biological Sciences", "AP/IB/Coll": "12", "Honors": "12", "App Deadline": "ED", "Home State": "CA"}, {"Class of": "2021", "Admission Decision": "Not Accepted", "GPA": "3.88", "Applied Test Optional": true, "SAT Single": 1410, "ACT": "", "Major": "Computer Science", "AP/IB/Coll": "15", "Honors": "4", "App Deadline": "ED", "Home State": "CA"}, {"Class of": "2021", "Admission Decision": "Not reported", "GPA": "3.4", "Applied Test Optional": false, "SAT Single": "", "ACT": "34", "Major": "Biological Sciences", "AP/IB/Coll": "10", "Honors": "9", "App Deadline": "", "Home State": "CA"}, {"Class of": "2021", "Admission Decision": "Not reported", "GPA": "3.91", "Applied Test Optional": true, "SAT Single": 1370, "ACT": "", "Major": "Engineering - Biomedical", "AP/IB/Coll": "26", "Honors": "8", "App Deadline": "", "Home State": "CA"}, {"Class of": "2021", "Admission Decision": "Not Accepted", "GPA": "3.58", "Applied Test Optional": false, "SAT Single": 1550, "ACT": "", "Major": "Business", "AP/IB/Coll": "11", "Honors": "8", "App Deadline": "ED", "Home State": "CA"}, {"Class of": "2021", "Admission Decision": "Waitlisted", "GPA": "4", "Applied Test Optional": false, "SAT Single": 1540, "ACT": "", "Major": "Computer Science", "AP/IB/Coll": "30", "Honors": "16", "App Deadline": "", "Home State": "CA"}, {"Class of": "2021", "Admission Decision": "Not Accepted", "GPA": "4", "Applied Test Optional": false, "SAT Single": "", "ACT": "35", "Major": "Computer Science", "AP/IB/Coll": "28", "Honors": "8", "App Deadline": "", "Home State": "WA"}, {"Class of": "2021", "Admission Decision": "Accepted", "GPA": "4", "Applied Test Optional": true, "SAT Single": "", "ACT": "", "Major": "Engineering - Civil", "AP/IB/Coll": "16", "Honors": "10", "App Deadline": "", "Home State": "MA"}, {"Class of": "2021", "Admission Decision": "Waitlisted", "GPA": "4", "Applied Test Optional": false, "SAT Single": 1580, "ACT": "", "Major": "Computer Science", "AP/IB/Coll": "20", "Honors": "10", "App Deadline": "EA", "Home State": "NJ"}, {"Class of": "2021", "Admission Decision": "Waitlisted", "GPA": "3.9", "Applied Test Optional": false, "SAT Single": 1520, "ACT": "", "Major": "Computer Science", "AP/IB/Coll": "26", "Honors": "10", "App Deadline": "", "Home State": "VA"}, {"Class of": "2021", "Admission Decision": "Waitlisted", "GPA": "3.93", "Applied Test Optional": false, "SAT Single": 1520, "ACT": "", "Major": "Computer Science", "AP/IB/Coll": "26", "Honors": "2", "App Deadline": "", "Home State": "CA"}, {"Class of": "2021", "Admission Decision": "Not Accepted", "GPA": "4", "Applied Test Optional": false, "SAT Single": "", "ACT": "", "Major": "Engineering - Chemical", "AP/IB/Coll": "18", "Honors": "10", "App Deadline": "", "Home State": "WA"}, {"Class of": "2021", "Admission Decision": "Not Accepted", "GPA": "3.42", "Applied Test Optional": false, "SAT Single": 1570, "ACT": "", "Major": "Economics", "AP/IB/Coll": "20", "Honors": "16", "App Deadline": "", "Home State": "NJ"}, {"Class of": "2021", "Admission Decision": "Not reported", "GPA": "3.77", "Applied Test Optional": true, "SAT Single": 1430, "ACT": "", "Major": "Business", "AP/IB/Coll": "16", "Honors": "18", "App Deadline": "", "Home State": "TX"}, {"Class of": "2021", "Admission Decision": "Waitlisted", "GPA": "3.46", "Applied Test Optional": false, "SAT Single": 1520, "ACT": "", "Major": "Psychology", "AP/IB/Coll": "9", "Honors": "10", "App Deadline": "ED", "Home State": "CA"}, {"Class of": "2021", "Admission Decision": "Waitlisted", "GPA": "3.83", "Applied Test Optional": false, "SAT Single": 1540, "ACT": "", "Major": "Computer Science", "AP/IB/Coll": "22", "Honors": "22", "App Deadline": "", "Home State": "NJ"}, {"Class of": "2021", "Admission Decision": "Waitlisted", "GPA": "3.92", "Applied Test Optional": false, "SAT Single": "", "ACT": "35", "Major": "Computer Science", "AP/IB/Coll": "24", "Honors": "20", "App Deadline": "", "Home State": "NJ"}, {"Class of": "2021", "Admission Decision": "Not reported", "GPA": "3.77", "Applied Test Optional": false, "SAT Single": 1570, "ACT": "", "Major": "Physics", "AP/IB/Coll": "14", "Honors": "", "App Deadline": "", "Home State": "NJ"}, {"Class of": "2021", "Admission Decision": "Waitlisted", "GPA": "3.8", "Applied Test Optional": true, "SAT Single": "", "ACT": "", "Major": "Computer Science", "AP/IB/Coll": "20", "Honors": "0", "App Deadline": "", "Home State": "CA"}, {"Class of": "2021", "Admission Decision": "Not Accepted", "GPA": "3.9", "Applied Test Optional": true, "SAT Single": "", "ACT": "", "Major": "Computer Information Systems", "AP/IB/Coll": "6", "Honors": "0", "App Deadline": "", "Home State": "CA"}, {"Class of": "2021", "Admission Decision": "Not Accepted", "GPA": "3.5", "Applied Test Optional": true, "SAT Single": "", "ACT": "", "Major": "Computer Science", "AP/IB/Coll": "6", "Honors": "0", "App Deadline": "ED", "Home State": "CA"}, {"Class of": "2021", "Admission Decision": "Waitlisted", "GPA": "3.9", "Applied Test Optional": false, "SAT Single": "", "ACT": "", "Major": "Business", "AP/IB/Coll": "18", "Honors": "16", "App Deadline": "", "Home State": "CA"}, {"Class of": "2021", "Admission Decision": "Waitlisted", "GPA": "3.58", "Applied Test Optional": true, "SAT Single": "", "ACT": "28", "Major": "Biological Sciences", "AP/IB/Coll": "14", "Honors": "14", "App Deadline": "", "Home State": "CA"}, {"Class of": "2021", "Admission Decision": "Not Accepted", "GPA": "3.9", "Applied Test Optional": false, "SAT Single": "", "ACT": "36", "Major": "Math", "AP/IB/Coll": "22", "Honors": "20", "App Deadline": "", "Home State": "MA"}, {"Class of": "2021", "Admission Decision": "Accepted", "GPA": "3.68", "Applied Test Optional": false, "SAT Single": "", "ACT": "33", "Major": "Engineering - Electrical", "AP/IB/Coll": "9", "Honors": "13", "App Deadline": "ED", "Home State": "MA"}, {"Class of": "2021", "Admission Decision": "Not Accepted", "GPA": "4", "Applied Test Optional": true, "SAT Single": 1370, "ACT": "", "Major": "Engineering - Electrical", "AP/IB/Coll": "14", "Honors": "24", "App Deadline": "", "Home State": "MA"}, {"Class of": "2021", "Admission Decision": "Not Accepted", "GPA": "3.58", "Applied Test Optional": true, "SAT Single": 1150, "ACT": "", "Major": "Economics", "AP/IB/Coll": "16", "Honors": "8", "App Deadline": "", "Home State": "TX"}, {"Class of": "2021", "Admission Decision": "Waitlisted", "GPA": "3.89", "Applied Test Optional": false, "SAT Single": 1570, "ACT": "", "Major": "Engineering - Mechanical", "AP/IB/Coll": "28", "Honors": "12", "App Deadline": "EA", "Home State": "NC"}, {"Class of": "2021", "Admission Decision": "Not Accepted", "GPA": "4", "Applied Test Optional": true, "SAT Single": "", "ACT": "", "Major": "Computer Science", "AP/IB/Coll": "18", "Honors": "0", "App Deadline": "", "Home State": "CA"}, {"Class of": "2021", "Admission Decision": "Not Accepted", "GPA": "4", "Applied Test Optional": true, "SAT Single": "", "ACT": "", "Major": "Computer Science", "AP/IB/Coll": "44", "Honors": "0", "App Deadline": "", "Home State": "CA"}, {"Class of": "2021", "Admission Decision": "Waitlisted", "GPA": "3.7", "Applied Test Optional": false, "SAT Single": "", "ACT": "36", "Major": "Engineering - Mechanical", "AP/IB/Coll": "8", "Honors": "12", "App Deadline": "", "Home State": "NJ"}, {"Class of": "2021", "Admission Decision": "Not Accepted", "GPA": "3.3", "Applied Test Optional": false, "SAT Single": 1500, "ACT": "", "Major": "Engineering - Chemical", "AP/IB/Coll": "18", "Honors": "12", "App Deadline": "", "Home State": "CA"}, {"Class of": "2021", "Admission Decision": "Waitlisted", "GPA": "3.5", "Applied Test Optional": false, "SAT Single": 1530, "ACT": "", "Major": "Business - Administration", "AP/IB/Coll": "14", "Honors": "14", "App Deadline": "", "Home State": "NJ"}, {"Class of": "2021", "Admission Decision": "Accepted", "GPA": "3.96", "Applied Test Optional": false, "SAT Single": "", "ACT": "35", "Major": "Material Science & Engineering", "AP/IB/Coll": "15", "Honors": "11", "App Deadline": "", "Home State": "NC"}, {"Class of": "2021", "Admission Decision": "Not Accepted", "GPA": "3.79", "Applied Test Optional": false, "SAT Single": 1520, "ACT": "", "Major": "Computer Science", "AP/IB/Coll": "13", "Honors": "13", "App Deadline": "ED", "Home State": "NC"}, {"Class of": "2021", "Admission Decision": "Waitlisted", "GPA": "4", "Applied Test Optional": false, "SAT Single": 1520, "ACT": "", "Major": "Computer Science", "AP/IB/Coll": "12", "Honors": "16", "App Deadline": "", "Home State": "NC"}, {"Class of": "2021", "Admission Decision": "Not Accepted", "GPA": "3.8", "Applied Test Optional": false, "SAT Single": 1490, "ACT": "", "Major": "Computer Science", "AP/IB/Coll": "6", "Honors": "7", "App Deadline": "ED", "Home State": "CA"}, {"Class of": "2021", "Admission Decision": "Waitlisted", "GPA": "4", "Applied Test Optional": false, "SAT Single": 1580, "ACT": "", "Major": "Computer Science", "AP/IB/Coll": "", "Honors": "", "App Deadline": "", "Home State": "NY"}, {"Class of": "2021", "Admission Decision": "Accepted", "GPA": "", "Applied Test Optional": false, "SAT Single": "", "ACT": "", "Major": "Engineering", "AP/IB/Coll": "14", "Honors": "12", "App Deadline": "Regular Decision", "Home State": "NY"}, {"Class of": "2021", "Admission Decision": "Deferred then withdrew", "GPA": "", "Applied Test Optional": false, "SAT Single": "", "ACT": "", "Major": "Computer Science", "AP/IB/Coll": "16", "Honors": "16", "App Deadline": "Early Decision", "Home State": "NY"}, {"Class of": "2021", "Admission Decision": "Not reported", "GPA": "", "Applied Test Optional": false, "SAT Single": "", "ACT": "", "Major": "Art", "AP/IB/Coll": "12", "Honors": "4", "App Deadline": "Regular Decision", "Home State": "NY"}, {"Class of": "2021", "Admission Decision": "Waitlisted", "GPA": "", "Applied Test Optional": false, "SAT Single": "", "ACT": "", "Major": "Mathematical Sciences", "AP/IB/Coll": "6", "Honors": "42", "App Deadline": "Regular Decision", "Home State": "NY"}]