[{"Class of": "2018", "Admission Decision": "Waitlisted", "GPA": "4", "SAT Single": "", "ACT": "31", "Major": "Business", "AP/IB/Coll": "20", "Honors": "0", "App Deadline": "", "Home State": "CA", "Applied Test Optional": null}, {"Class of": "2019", "Admission Decision": "Not Accepted", "GPA": "3.96", "SAT Single": 1440, "ACT": "32", "Major": "Political Science", "AP/IB/Coll": "18", "Honors": "16", "App Deadline": "", "Home State": "CA", "Applied Test Optional": null}, {"Class of": "2021", "Admission Decision": "Not Accepted", "GPA": "3.75", "Applied Test Optional": true, "SAT Single": "", "ACT": "", "Major": "Biology", "AP/IB/Coll": "16", "Honors": "12", "App Deadline": "", "Home State": "MD"}, {"Class of": "2021", "Admission Decision": "Not Accepted", "GPA": "3.99", "Applied Test Optional": false, "SAT Single": "", "ACT": "", "Major": "Philosophy - Political Science", "AP/IB/Coll": "16", "Honors": "14", "App Deadline": "", "Home State": "CA"}]